{"version_info":{"id":19,"version_hash":"4445e789","version_folder":"Games/Deadlock/DeadlockAugust22025","created_at":"2025-09-16T03:50:05.663748+00:00"},"export_timestamp":"2025-10-02T16:05:51.677Z","delta":{"isFirstExport":false,"changes":{"voicelines":{"atlas_match_start_atlas_shiv_convo02_01.mp3":{"previous_count":10,"current_count":12,"delta":2},"atlas_select_01.mp3":{"previous_count":6,"current_count":7,"delta":1},"atlas_select_02.mp3":{"previous_count":5,"current_count":6,"delta":1},"atlas_select_03.mp3":{"previous_count":5,"current_count":6,"delta":1},"atlas_select_04.mp3":{"previous_count":3,"current_count":4,"delta":1},"atlas_select_05.mp3":{"previous_count":2,"current_count":3,"delta":1},"atlas_select_06.mp3":{"previous_count":2,"current_count":3,"delta":1},"atlas_select_07.mp3":{"previous_count":3,"current_count":4,"delta":1},"atlas_select_08.mp3":{"previous_count":2,"current_count":3,"delta":1},"atlas_select_09.mp3":{"previous_count":2,"current_count":3,"delta":1},"atlas_select_10.mp3":{"previous_count":1,"current_count":2,"delta":1},"atlas_select_11.mp3":{"previous_count":1,"current_count":2,"delta":1},"atlas_upgrade_power1_02.mp3":{"previous_count":2,"current_count":3,"delta":1},"atlas_upgrade_power3_06.mp3":{"previous_count":2,"current_count":3,"delta":1},"atlas_upgrade_power3_10.mp3":{"previous_count":0,"current_count":1,"delta":1},"bebop_select_01.mp3":{"previous_count":3,"current_count":4,"delta":1},"bebop_select_02.mp3":{"previous_count":3,"current_count":4,"delta":1},"bebop_select_03.mp3":{"previous_count":1,"current_count":2,"delta":1},"bebop_select_04.mp3":{"previous_count":0,"current_count":1,"delta":1},"bebop_select_05.mp3":{"previous_count":1,"current_count":2,"delta":1},"bebop_select_06.mp3":{"previous_count":1,"current_count":2,"delta":1},"bebop_select_07.mp3":{"previous_count":1,"current_count":2,"delta":1},"bebop_select_08.mp3":{"previous_count":0,"current_count":1,"delta":1},"bebop_select_09.mp3":{"previous_count":2,"current_count":3,"delta":1},"bebop_select_10.mp3":{"previous_count":1,"current_count":2,"delta":1},"bookworm_match_start_bookworm_viper_convo01_01.mp3":{"previous_count":12,"current_count":13,"delta":1},"bookworm_match_start_bookworm_viper_convo01_03.mp3":{"previous_count":13,"current_count":14,"delta":1},"bookworm_match_start_bookworm_viper_convo02_02.mp3":{"previous_count":7,"current_count":8,"delta":1},"bookworm_match_start_bookworm_viper_convo02_04.mp3":{"previous_count":7,"current_count":8,"delta":1},"bookworm_match_start_bookworm_viper_convo02_06.mp3":{"previous_count":6,"current_count":7,"delta":1},"bookworm_match_start_bookworm_viper_convo02_08.mp3":{"previous_count":7,"current_count":8,"delta":1},"bookworm_match_start_bookworm_viper_convo03_02.mp3":{"previous_count":6,"current_count":7,"delta":1},"bookworm_match_start_bookworm_viper_convo03_04.mp3":{"previous_count":5,"current_count":6,"delta":1},"bookworm_match_start_bookworm_viper_convo03_06.mp3":{"previous_count":5,"current_count":6,"delta":1},"doorman_ally_krill_grab_mid_enemy_ult_01.mp3":{"previous_count":2,"current_count":3,"delta":1},"doorman_ally_skyrunner_killed_in_lane_01.mp3":{"previous_count":4,"current_count":5,"delta":1},"doorman_desperation_power4_01.mp3":{"previous_count":29,"current_count":30,"delta":1},"doorman_desperation_power4_02.mp3":{"previous_count":18,"current_count":19,"delta":1},"doorman_desperation_power4_03.mp3":{"previous_count":25,"current_count":26,"delta":1},"doorman_killstreak_high_03.mp3":{"previous_count":22,"current_count":23,"delta":1},"doorman_killstreak_mid_02.mp3":{"previous_count":11,"current_count":12,"delta":1},"doorman_killstreak_mid_03.mp3":{"previous_count":11,"current_count":12,"delta":1},"doorman_killstreak_start_03.mp3":{"previous_count":7,"current_count":8,"delta":1},"doorman_killstreak_start_04.mp3":{"previous_count":10,"current_count":11,"delta":1},"doorman_leave_base_03.mp3":{"previous_count":2,"current_count":3,"delta":1},"doorman_match_start_doorman_bebop_convo02_06.mp3":{"previous_count":15,"current_count":16,"delta":1},"doorman_match_start_vampirebat_doorman_convo01_01.mp3":{"previous_count":23,"current_count":24,"delta":1},"doorman_match_start_vampirebat_doorman_convo01_03.mp3":{"previous_count":20,"current_count":21,"delta":1},"doorman_match_start_vampirebat_doorman_convo02_02.mp3":{"previous_count":17,"current_count":18,"delta":1},"doorman_match_start_vampirebat_doorman_convo03_02.mp3":{"previous_count":18,"current_count":19,"delta":1},"doorman_match_start_vampirebat_doorman_convo03_04.mp3":{"previous_count":18,"current_count":19,"delta":1},"doorman_parry_01.mp3":{"previous_count":8,"current_count":9,"delta":1},"doorman_parry_03.mp3":{"previous_count":10,"current_count":11,"delta":1},"doorman_ping_use_ability4_07.mp3":{"previous_count":1,"current_count":2,"delta":1},"doorman_power4_on_magician_savannah.mp3":{"previous_count":9,"current_count":10,"delta":1},"doorman_revenge_kill.mp3":{"previous_count":6,"current_count":7,"delta":1},"doorman_select_01.mp3":{"previous_count":9,"current_count":10,"delta":1},"doorman_select_02.mp3":{"previous_count":5,"current_count":6,"delta":1},"doorman_select_03.mp3":{"previous_count":4,"current_count":5,"delta":1},"doorman_select_04.mp3":{"previous_count":3,"current_count":4,"delta":1},"doorman_select_05.mp3":{"previous_count":3,"current_count":4,"delta":1},"doorman_select_06.mp3":{"previous_count":2,"current_count":3,"delta":1},"doorman_select_07.mp3":{"previous_count":3,"current_count":4,"delta":1},"doorman_select_08.mp3":{"previous_count":2,"current_count":3,"delta":1},"doorman_select_09.mp3":{"previous_count":2,"current_count":3,"delta":1},"doorman_select_10.mp3":{"previous_count":2,"current_count":3,"delta":1},"doorman_unselect_08.mp3":{"previous_count":3,"current_count":4,"delta":1},"doorman_use_power4_03.mp3":{"previous_count":6,"current_count":7,"delta":1},"doorman_use_power4_04.mp3":{"previous_count":8,"current_count":9,"delta":1},"doorman_use_power4_06.mp3":{"previous_count":6,"current_count":7,"delta":1},"doorman_use_power4_10.mp3":{"previous_count":8,"current_count":9,"delta":1},"drifter_select_01.mp3":{"previous_count":12,"current_count":13,"delta":1},"drifter_select_02.mp3":{"previous_count":7,"current_count":8,"delta":1},"drifter_select_03.mp3":{"previous_count":13,"current_count":14,"delta":1},"drifter_select_04.mp3":{"previous_count":10,"current_count":11,"delta":1},"drifter_select_05.mp3":{"previous_count":5,"current_count":6,"delta":1},"drifter_select_06.mp3":{"previous_count":7,"current_count":8,"delta":1},"drifter_select_07.mp3":{"previous_count":3,"current_count":4,"delta":1},"drifter_select_08.mp3":{"previous_count":3,"current_count":4,"delta":1},"drifter_select_09.mp3":{"previous_count":3,"current_count":4,"delta":1},"drifter_select_10.mp3":{"previous_count":6,"current_count":7,"delta":1},"dynamo_match_start_dynamo_shiv_convo02_02.mp3":{"previous_count":5,"current_count":6,"delta":1},"dynamo_select_01.mp3":{"previous_count":3,"current_count":4,"delta":1},"dynamo_select_02.mp3":{"previous_count":3,"current_count":4,"delta":1},"dynamo_select_03.mp3":{"previous_count":2,"current_count":3,"delta":1},"dynamo_select_04.mp3":{"previous_count":1,"current_count":2,"delta":1},"dynamo_select_05.mp3":{"previous_count":1,"current_count":2,"delta":1},"dynamo_select_06.mp3":{"previous_count":0,"current_count":1,"delta":1},"dynamo_select_07.mp3":{"previous_count":1,"current_count":2,"delta":1},"dynamo_select_08.mp3":{"previous_count":0,"current_count":1,"delta":1},"dynamo_select_09.mp3":{"previous_count":0,"current_count":1,"delta":1},"dynamo_select_10.mp3":{"previous_count":0,"current_count":1,"delta":1},"hornet_match_start_vampirebat_hornet_convo01_02.mp3":{"previous_count":8,"current_count":9,"delta":1},"hornet_match_start_viper_hornet_convo01_02.mp3":{"previous_count":7,"current_count":8,"delta":1},"hornet_match_start_viper_hornet_convo01_04.mp3":{"previous_count":6,"current_count":7,"delta":1},"hornet_match_start_viper_hornet_convo02_01.mp3":{"previous_count":7,"current_count":8,"delta":1},"hornet_match_start_viper_hornet_convo02_03.mp3":{"previous_count":8,"current_count":9,"delta":1},"hornet_match_start_viper_hornet_convo03_01.mp3":{"previous_count":4,"current_count":5,"delta":1},"lash_ally_viper_killed_in_lane_02.mp3":{"previous_count":3,"current_count":4,"delta":1},"lash_kill_viper_05.mp3":{"previous_count":7,"current_count":8,"delta":1},"lash_match_start_viper_lash_convo01_02.mp3":{"previous_count":15,"current_count":16,"delta":1},"lash_match_start_viper_lash_convo02_01.mp3":{"previous_count":8,"current_count":9,"delta":1},"lash_match_start_viper_lash_convo02_03.mp3":{"previous_count":8,"current_count":9,"delta":1},"lash_match_start_viper_lash_convo02_05.mp3":{"previous_count":10,"current_count":11,"delta":1},"lash_match_start_viper_lash_convo03_02.mp3":{"previous_count":10,"current_count":11,"delta":1},"lash_match_start_viper_lash_convo03_04.mp3":{"previous_count":11,"current_count":12,"delta":1},"lash_match_start_viper_lash_convo03_06.mp3":{"previous_count":11,"current_count":12,"delta":1},"lash_upgrade_power4_10.mp3":{"previous_count":1,"current_count":3,"delta":2},"mirage_match_start_viper_mirage_convo01_01.mp3":{"previous_count":9,"current_count":10,"delta":1},"mirage_match_start_viper_mirage_convo02_02.mp3":{"previous_count":11,"current_count":12,"delta":1},"mirage_match_start_viper_mirage_convo02_04.mp3":{"previous_count":11,"current_count":12,"delta":1},"mirage_match_start_viper_mirage_convo03_02.mp3":{"previous_count":10,"current_count":11,"delta":1},"mirage_match_start_viper_mirage_convo03_04.mp3":{"previous_count":11,"current_count":12,"delta":1},"mirage_match_start_viper_mirage_convo03_06.mp3":{"previous_count":12,"current_count":13,"delta":1},"nano_select_01.mp3":{"previous_count":0,"current_count":1,"delta":1},"nano_select_02.mp3":{"previous_count":2,"current_count":3,"delta":1},"nano_select_03.mp3":{"previous_count":2,"current_count":3,"delta":1},"nano_select_04.mp3":{"previous_count":1,"current_count":2,"delta":1},"nano_select_05.mp3":{"previous_count":1,"current_count":2,"delta":1},"nano_select_06.mp3":{"previous_count":1,"current_count":2,"delta":1},"nano_select_07.mp3":{"previous_count":1,"current_count":2,"delta":1},"nano_select_08.mp3":{"previous_count":1,"current_count":2,"delta":1},"nano_select_09.mp3":{"previous_count":1,"current_count":2,"delta":1},"nano_select_10.mp3":{"previous_count":1,"current_count":2,"delta":1},"orion_match_start_orion_shiv_convo01_01.mp3":{"previous_count":6,"current_count":7,"delta":1},"patron_female_ally_viper_killing_streak_01.mp3":{"previous_count":0,"current_count":1,"delta":1},"patron_female_ally_viper_killing_streak_02.mp3":{"previous_count":5,"current_count":6,"delta":1},"patron_female_ally_viper_killing_streak_03.mp3":{"previous_count":0,"current_count":1,"delta":1},"patron_female_bespoke_ally_update_viper.mp3":{"previous_count":1,"current_count":2,"delta":1},"punkgoat_select_01.mp3":{"previous_count":8,"current_count":9,"delta":1},"punkgoat_select_02.mp3":{"previous_count":7,"current_count":8,"delta":1},"punkgoat_select_03.mp3":{"previous_count":3,"current_count":4,"delta":1},"punkgoat_select_04.mp3":{"previous_count":1,"current_count":2,"delta":1},"punkgoat_select_05.mp3":{"previous_count":2,"current_count":3,"delta":1},"punkgoat_select_06.mp3":{"previous_count":3,"current_count":4,"delta":1},"punkgoat_select_07.mp3":{"previous_count":5,"current_count":6,"delta":1},"punkgoat_select_08.mp3":{"previous_count":3,"current_count":4,"delta":1},"punkgoat_select_09.mp3":{"previous_count":4,"current_count":5,"delta":1},"punkgoat_select_10.mp3":{"previous_count":4,"current_count":5,"delta":1},"shiv_match_start_atlas_shiv_convo02_02.mp3":{"previous_count":14,"current_count":19,"delta":5},"shiv_match_start_dynamo_shiv_convo02_01.mp3":{"previous_count":7,"current_count":8,"delta":1},"shiv_match_start_dynamo_shiv_convo02_03.mp3":{"previous_count":5,"current_count":6,"delta":1},"synth_ally_atlas_killed_in_lane_01.mp3":{"previous_count":0,"current_count":1,"delta":1},"synth_ally_nano_killed_in_lane_01.mp3":{"previous_count":2,"current_count":3,"delta":1},"synth_ally_nano_pass_on_zipline_01.mp3":{"previous_count":2,"current_count":3,"delta":1},"synth_ally_slork_pass_on_zipline_01.mp3":{"previous_count":1,"current_count":2,"delta":1},"synth_kill_nano_01.mp3":{"previous_count":1,"current_count":2,"delta":1},"synth_kill_nano_02.mp3":{"previous_count":0,"current_count":1,"delta":1},"synth_kill_nano_03.mp3":{"previous_count":1,"current_count":2,"delta":1},"synth_kill_nano_05.mp3":{"previous_count":2,"current_count":3,"delta":1},"synth_kill_operative_02.mp3":{"previous_count":3,"current_count":4,"delta":1},"synth_kill_operative_03.mp3":{"previous_count":2,"current_count":3,"delta":1},"synth_kill_operative_04.mp3":{"previous_count":1,"current_count":2,"delta":1},"synth_kill_operative_05.mp3":{"previous_count":1,"current_count":2,"delta":1},"synth_kill_slork_02.mp3":{"previous_count":1,"current_count":2,"delta":1},"synth_kill_slork_03.mp3":{"previous_count":1,"current_count":2,"delta":1},"synth_kill_slork_04.mp3":{"previous_count":1,"current_count":2,"delta":1},"synth_kill_slork_05.mp3":{"previous_count":1,"current_count":2,"delta":1},"synth_select_01.mp3":{"previous_count":2,"current_count":3,"delta":1},"synth_select_02.mp3":{"previous_count":1,"current_count":2,"delta":1},"synth_select_03.mp3":{"previous_count":0,"current_count":1,"delta":1},"synth_select_04.mp3":{"previous_count":0,"current_count":1,"delta":1},"synth_select_05.mp3":{"previous_count":0,"current_count":1,"delta":1},"synth_select_06.mp3":{"previous_count":0,"current_count":1,"delta":1},"synth_select_07.mp3":{"previous_count":0,"current_count":1,"delta":1},"synth_select_08.mp3":{"previous_count":0,"current_count":1,"delta":1},"synth_select_09.mp3":{"previous_count":0,"current_count":1,"delta":1},"synth_select_10.mp3":{"previous_count":0,"current_count":1,"delta":1},"synth_select_11.mp3":{"previous_count":0,"current_count":1,"delta":1},"vampirebat_ally_bookworm_pass_on_zipline_01.mp3":{"previous_count":2,"current_count":3,"delta":1},"vampirebat_kill_bookworm_02.mp3":{"previous_count":7,"current_count":8,"delta":1},"vampirebat_kill_bookworm_04.mp3":{"previous_count":4,"current_count":5,"delta":1},"vampirebat_match_start_vampirebat_doorman_convo01_02.mp3":{"previous_count":24,"current_count":25,"delta":1},"vampirebat_match_start_vampirebat_doorman_convo02_01.mp3":{"previous_count":19,"current_count":20,"delta":1},"vampirebat_match_start_vampirebat_doorman_convo02_03.mp3":{"previous_count":17,"current_count":18,"delta":1},"vampirebat_match_start_vampirebat_doorman_convo03_01.mp3":{"previous_count":20,"current_count":21,"delta":1},"vampirebat_match_start_vampirebat_doorman_convo03_03.mp3":{"previous_count":18,"current_count":19,"delta":1},"viper_match_start_bookworm_viper_convo01_02.mp3":{"previous_count":18,"current_count":19,"delta":1},"viper_match_start_bookworm_viper_convo02_01.mp3":{"previous_count":8,"current_count":9,"delta":1},"viper_match_start_bookworm_viper_convo02_03.mp3":{"previous_count":7,"current_count":8,"delta":1},"viper_match_start_bookworm_viper_convo02_05.mp3":{"previous_count":8,"current_count":9,"delta":1},"viper_match_start_bookworm_viper_convo02_07.mp3":{"previous_count":8,"current_count":9,"delta":1},"viper_match_start_bookworm_viper_convo02_09.mp3":{"previous_count":8,"current_count":9,"delta":1},"viper_match_start_bookworm_viper_convo03_01.mp3":{"previous_count":6,"current_count":7,"delta":1},"viper_match_start_bookworm_viper_convo03_03.mp3":{"previous_count":5,"current_count":6,"delta":1},"viper_match_start_bookworm_viper_convo03_05.mp3":{"previous_count":5,"current_count":6,"delta":1},"viper_match_start_bookworm_viper_convo03_07.mp3":{"previous_count":5,"current_count":6,"delta":1},"viper_match_start_viper_atlas_convo01_02.mp3":{"previous_count":6,"current_count":7,"delta":1},"viper_match_start_viper_atlas_convo01_04.mp3":{"previous_count":5,"current_count":6,"delta":1},"viper_match_start_viper_hornet_convo01_01.mp3":{"previous_count":8,"current_count":9,"delta":1},"viper_match_start_viper_hornet_convo01_03.mp3":{"previous_count":6,"current_count":7,"delta":1},"viper_match_start_viper_hornet_convo01_05.mp3":{"previous_count":6,"current_count":7,"delta":1},"viper_match_start_viper_hornet_convo02_02.mp3":{"previous_count":8,"current_count":9,"delta":1},"viper_match_start_viper_hornet_convo02_04.mp3":{"previous_count":9,"current_count":10,"delta":1},"viper_match_start_viper_hornet_convo03_02.mp3":{"previous_count":3,"current_count":4,"delta":1},"viper_match_start_viper_lash_convo01_01.mp3":{"previous_count":14,"current_count":15,"delta":1},"viper_match_start_viper_lash_convo01_03.mp3":{"previous_count":16,"current_count":17,"delta":1},"viper_match_start_viper_lash_convo02_02.mp3":{"previous_count":8,"current_count":9,"delta":1},"viper_match_start_viper_lash_convo02_04.mp3":{"previous_count":9,"current_count":10,"delta":1},"viper_match_start_viper_lash_convo02_06.mp3":{"previous_count":7,"current_count":8,"delta":1},"viper_match_start_viper_lash_convo03_01.mp3":{"previous_count":8,"current_count":9,"delta":1},"viper_match_start_viper_lash_convo03_03.mp3":{"previous_count":9,"current_count":10,"delta":1},"viper_match_start_viper_lash_convo03_05.mp3":{"previous_count":9,"current_count":10,"delta":1},"viper_match_start_viper_mirage_convo01_02.mp3":{"previous_count":10,"current_count":11,"delta":1},"viper_match_start_viper_mirage_convo02_01.mp3":{"previous_count":11,"current_count":12,"delta":1},"viper_match_start_viper_mirage_convo02_03.mp3":{"previous_count":11,"current_count":12,"delta":1},"viper_match_start_viper_mirage_convo02_05.mp3":{"previous_count":15,"current_count":16,"delta":1},"viper_match_start_viper_mirage_convo03_01.mp3":{"previous_count":10,"current_count":11,"delta":1},"viper_match_start_viper_mirage_convo03_03.mp3":{"previous_count":10,"current_count":11,"delta":1},"viper_match_start_viper_mirage_convo03_05.mp3":{"previous_count":12,"current_count":13,"delta":1},"viper_match_start_viper_wraith_convo01_02.mp3":{"previous_count":4,"current_count":5,"delta":1},"viper_match_start_viper_wraith_convo02_01.mp3":{"previous_count":3,"current_count":4,"delta":1},"viper_match_start_viper_wraith_convo02_03.mp3":{"previous_count":2,"current_count":3,"delta":1},"viper_match_start_viper_wraith_convo02_05.mp3":{"previous_count":2,"current_count":3,"delta":1},"viper_match_start_viper_wraith_convo03_01.mp3":{"previous_count":2,"current_count":4,"delta":2},"viper_match_start_viper_wraith_convo03_03.mp3":{"previous_count":2,"current_count":3,"delta":1},"wraith_match_start_viper_wraith_convo01_01.mp3":{"previous_count":3,"current_count":4,"delta":1},"wraith_match_start_viper_wraith_convo02_02.mp3":{"previous_count":2,"current_count":3,"delta":1},"wraith_match_start_viper_wraith_convo02_04.mp3":{"previous_count":2,"current_count":3,"delta":1},"wraith_match_start_viper_wraith_convo03_02.mp3":{"previous_count":2,"current_count":3,"delta":1},"wraith_match_start_viper_wraith_convo03_04.mp3":{"previous_count":7,"current_count":8,"delta":1}},"conversations":{"abrams_shiv_convo02":{"previous_count":12,"current_count":13,"delta":1},"abrams_viper_convo01":{"previous_count":5,"current_count":6,"delta":1},"bebop_doorman_convo02":{"previous_count":16,"current_count":17,"delta":1},"doorman_mina_convo01":{"previous_count":24,"current_count":25,"delta":1},"doorman_mina_convo02":{"previous_count":18,"current_count":19,"delta":1},"doorman_mina_convo03":{"previous_count":18,"current_count":19,"delta":1},"dynamo_shiv_convo02":{"previous_count":6,"current_count":7,"delta":1},"grey talon_shiv_convo01":{"previous_count":7,"current_count":8,"delta":1},"lash_viper_convo01":{"previous_count":16,"current_count":17,"delta":1},"lash_viper_convo02":{"previous_count":10,"current_count":11,"delta":1},"lash_viper_convo03":{"previous_count":11,"current_count":12,"delta":1},"mina_vindicta_convo01":{"previous_count":7,"current_count":8,"delta":1},"mirage_viper_convo01":{"previous_count":10,"current_count":11,"delta":1},"mirage_viper_convo02":{"previous_count":11,"current_count":12,"delta":1},"mirage_viper_convo03":{"previous_count":11,"current_count":12,"delta":1},"paige_viper_convo01":{"previous_count":11,"current_count":12,"delta":1},"paige_viper_convo02":{"previous_count":9,"current_count":10,"delta":1},"paige_viper_convo03":{"previous_count":6,"current_count":7,"delta":1},"vindicta_viper_convo01":{"previous_count":7,"current_count":8,"delta":1},"vindicta_viper_convo02":{"previous_count":9,"current_count":10,"delta":1},"vindicta_viper_convo03":{"previous_count":4,"current_count":5,"delta":1},"viper_wraith_convo01":{"previous_count":3,"current_count":4,"delta":1},"viper_wraith_convo02":{"previous_count":2,"current_count":3,"delta":1},"viper_wraith_convo03":{"previous_count":6,"current_count":7,"delta":1}},"character_totals":{"abrams":{"previous_count":634,"current_count":635,"delta":1},"calico":{"previous_count":279,"current_count":285,"delta":6},"fathom":{"previous_count":105,"current_count":110,"delta":5},"krill":{"previous_count":339,"current_count":340,"delta":1},"lash":{"previous_count":544,"current_count":548,"delta":4},"operative":{"previous_count":60,"current_count":64,"delta":4},"paige":{"previous_count":300,"current_count":303,"delta":3},"sinclair (savannah)":{"previous_count":16,"current_count":17,"delta":1},"viper":{"previous_count":314,"current_count":318,"delta":4}}}}}