{"version_info":{"id":19,"version_hash":"4445e789","version_folder":"Games/Deadlock/DeadlockAugust22025","created_at":"2025-09-16T03:50:05.663748+00:00"},"export_timestamp":"2025-10-03T09:05:21.116Z","delta":{"isFirstExport":false,"changes":{"voicelines":{"bebop_match_start_bebop_ghost_convo01_02.mp3":{"previous_count":10,"current_count":12,"delta":2},"doorman_use_power4_05.mp3":{"previous_count":8,"current_count":9,"delta":1},"mirage_ally_haze_pass_on_zipline_01.mp3":{"previous_count":0,"current_count":1,"delta":1},"mirage_interrupt_04.mp3":{"previous_count":1,"current_count":2,"delta":1},"mirage_interrupt_05.mp3":{"previous_count":0,"current_count":1,"delta":1},"mirage_kill_anyhero_01.mp3":{"previous_count":2,"current_count":3,"delta":1},"mirage_kill_anyhero_02.mp3":{"previous_count":3,"current_count":4,"delta":1},"mirage_kill_anyhero_03.mp3":{"previous_count":2,"current_count":3,"delta":1},"mirage_kill_anyhero_04.mp3":{"previous_count":2,"current_count":3,"delta":1},"mirage_kill_anyhero_05.mp3":{"previous_count":2,"current_count":3,"delta":1},"mirage_kill_anyhero_06.mp3":{"previous_count":2,"current_count":3,"delta":1},"mirage_kill_anyhero_07.mp3":{"previous_count":2,"current_count":3,"delta":1},"mirage_kill_anyhero_08.mp3":{"previous_count":2,"current_count":3,"delta":1},"mirage_kill_anyhero_09.mp3":{"previous_count":2,"current_count":3,"delta":1},"mirage_kill_anyhero_10.mp3":{"previous_count":1,"current_count":2,"delta":1},"mirage_kill_haze_01.mp3":{"previous_count":1,"current_count":2,"delta":1},"mirage_kill_haze_03.mp3":{"previous_count":0,"current_count":1,"delta":1},"mirage_kill_vampirebat_02.mp3":{"previous_count":1,"current_count":2,"delta":1},"mirage_kill_vampirebat_03.mp3":{"previous_count":1,"current_count":2,"delta":1},"mirage_kill_vampirebat_04.mp3":{"previous_count":1,"current_count":2,"delta":1},"mirage_kill_vampirebat_05.mp3":{"previous_count":1,"current_count":2,"delta":1},"mirage_last_one_standing_01.mp3":{"previous_count":2,"current_count":3,"delta":1},"mirage_last_one_standing_02.mp3":{"previous_count":2,"current_count":3,"delta":1},"mirage_last_one_standing_03.mp3":{"previous_count":1,"current_count":2,"delta":1},"mirage_melee_kill_01.mp3":{"previous_count":1,"current_count":2,"delta":1},"mirage_melee_kill_02.mp3":{"previous_count":1,"current_count":2,"delta":1},"mirage_melee_kill_03.mp3":{"previous_count":1,"current_count":2,"delta":1},"mirage_melee_kill_04.mp3":{"previous_count":1,"current_count":2,"delta":1},"mirage_melee_kill_05.mp3":{"previous_count":1,"current_count":2,"delta":1},"mirage_near_miss_01.mp3":{"previous_count":3,"current_count":4,"delta":1},"mirage_near_miss_02.mp3":{"previous_count":1,"current_count":2,"delta":1},"mirage_near_miss_03.mp3":{"previous_count":1,"current_count":2,"delta":1},"mirage_near_miss_04.mp3":{"previous_count":3,"current_count":4,"delta":1},"mirage_near_miss_05.mp3":{"previous_count":2,"current_count":3,"delta":1},"mirage_outnumbered_01.mp3":{"previous_count":2,"current_count":4,"delta":2},"mirage_outnumbered_02.mp3":{"previous_count":1,"current_count":2,"delta":1},"mirage_outnumbered_03.mp3":{"previous_count":2,"current_count":3,"delta":1},"mirage_parry_01.mp3":{"previous_count":4,"current_count":5,"delta":1},"mirage_parry_02.mp3":{"previous_count":3,"current_count":4,"delta":1},"mirage_parry_03.mp3":{"previous_count":3,"current_count":4,"delta":1},"mirage_ping_haze_check_items.mp3":{"previous_count":0,"current_count":1,"delta":1},"mirage_revenge_kill.mp3":{"previous_count":4,"current_count":5,"delta":1},"patron_female_ally_punkgoat_killing_streak_01.mp3":{"previous_count":3,"current_count":4,"delta":1},"patron_female_ally_punkgoat_killing_streak_02.mp3":{"previous_count":2,"current_count":3,"delta":1},"patron_female_ally_punkgoat_killing_streak_03.mp3":{"previous_count":3,"current_count":4,"delta":1},"patron_female_ally_punkgoat_start_01.mp3":{"previous_count":3,"current_count":4,"delta":1},"patron_female_ally_punkgoat_start_02.mp3":{"previous_count":1,"current_count":2,"delta":1},"patron_female_ally_viper_killing_streak_02.mp3":{"previous_count":6,"current_count":7,"delta":1},"patron_female_ally_viper_killing_streak_03.mp3":{"previous_count":1,"current_count":2,"delta":1},"patron_female_ally_viper_start_01.mp3":{"previous_count":0,"current_count":1,"delta":1},"patron_female_ally_wrecker_killing_streak_01.mp3":{"previous_count":2,"current_count":3,"delta":1},"patron_female_bespoke_ally_update_punkgoat.mp3":{"previous_count":5,"current_count":6,"delta":1},"patron_female_enemy_punkgoat_killing_streak_high_01.mp3":{"previous_count":11,"current_count":12,"delta":1},"patron_female_enemy_punkgoat_killing_streak_low_01.mp3":{"previous_count":2,"current_count":3,"delta":1},"patron_female_enemy_punkgoat_killing_streak_medium_01.mp3":{"previous_count":3,"current_count":4,"delta":1},"patron_female_enemy_viper_killing_streak_high_01.mp3":{"previous_count":1,"current_count":2,"delta":1},"patron_female_enemy_viper_killing_streak_low_01.mp3":{"previous_count":0,"current_count":1,"delta":1},"patron_female_enemy_viper_killing_streak_medium_01.mp3":{"previous_count":0,"current_count":1,"delta":1},"patron_male_ally_punkgoat_killing_streak_01.mp3":{"previous_count":5,"current_count":7,"delta":2},"patron_male_ally_punkgoat_killing_streak_02.mp3":{"previous_count":2,"current_count":3,"delta":1},"patron_male_ally_punkgoat_killing_streak_03.mp3":{"previous_count":4,"current_count":5,"delta":1},"patron_male_ally_punkgoat_start_01.mp3":{"previous_count":5,"current_count":6,"delta":1},"patron_male_ally_punkgoat_start_05.mp3":{"previous_count":1,"current_count":2,"delta":1},"patron_male_ally_viper_killing_streak_02.mp3":{"previous_count":3,"current_count":4,"delta":1},"patron_male_ally_viper_killing_streak_03.mp3":{"previous_count":2,"current_count":3,"delta":1},"patron_male_ally_viscous_killing_streak_01.mp3":{"previous_count":2,"current_count":4,"delta":2},"patron_male_ally_viscous_killing_streak_03.mp3":{"previous_count":1,"current_count":2,"delta":1},"patron_male_enemy_punkgoat_killing_streak_high_01.mp3":{"previous_count":14,"current_count":15,"delta":1},"patron_male_enemy_punkgoat_killing_streak_low_01.mp3":{"previous_count":6,"current_count":7,"delta":1},"patron_male_enemy_punkgoat_killing_streak_medium_01.mp3":{"previous_count":8,"current_count":9,"delta":1},"patron_male_enemy_viper_killing_streak_high_01.mp3":{"previous_count":3,"current_count":4,"delta":1},"patron_male_enemy_viper_killing_streak_low_01.mp3":{"previous_count":3,"current_count":4,"delta":1},"patron_male_enemy_viscous_killing_streak_medium_01.mp3":{"previous_count":1,"current_count":2,"delta":1}},"conversations":{"bebop_lady geist_convo01":{"previous_count":8,"current_count":9,"delta":1}},"character_totals":{"billy":{"previous_count":544,"current_count":562,"delta":18},"haze":{"previous_count":413,"current_count":417,"delta":4},"mina":{"previous_count":497,"current_count":501,"delta":4},"viper":{"previous_count":367,"current_count":377,"delta":10},"viscous":{"previous_count":389,"current_count":393,"delta":4},"wrecker":{"previous_count":162,"current_count":163,"delta":1}}}}}