{"version_info":{"id":19,"version_hash":"4445e789","version_folder":"Games/Deadlock/DeadlockAugust22025","created_at":"2025-09-16T03:50:05.663748+00:00"},"export_timestamp":"2025-09-30T14:06:12.335Z","delta":{"isFirstExport":false,"changes":{"voicelines":{"astro_ally_warden_big_ult_02.mp3":{"previous_count":1,"current_count":2,"delta":1},"astro_kill_warden_03.mp3":{"previous_count":0,"current_count":1,"delta":1},"astro_match_start_gigawatt_astro_convo01_02.mp3":{"previous_count":2,"current_count":3,"delta":1},"atlas_ally_warden_big_ult_01.mp3":{"previous_count":2,"current_count":3,"delta":1},"atlas_ally_warden_big_ult_02.mp3":{"previous_count":0,"current_count":1,"delta":1},"atlas_ally_warden_big_ult_03.mp3":{"previous_count":1,"current_count":2,"delta":1},"atlas_enemy_warden_see_ult_01_alt_01.mp3":{"previous_count":0,"current_count":1,"delta":1},"atlas_enemy_warden_see_ult_01.mp3":{"previous_count":0,"current_count":1,"delta":1},"atlas_enemy_warden_see_ult_02.mp3":{"previous_count":1,"current_count":2,"delta":1},"atlas_enemy_warden_see_ult_03.mp3":{"previous_count":0,"current_count":1,"delta":1},"atlas_kill_warden_01.mp3":{"previous_count":1,"current_count":2,"delta":1},"atlas_kill_warden_03.mp3":{"previous_count":0,"current_count":1,"delta":1},"atlas_kill_warden_05.mp3":{"previous_count":1,"current_count":2,"delta":1},"atlas_match_start_atlas_dynamo_oathkeeper_convo01_02.mp3":{"previous_count":4,"current_count":5,"delta":1},"atlas_match_start_atlas_dynamo_oathkeeper_convo01_04.mp3":{"previous_count":4,"current_count":5,"delta":1},"atlas_match_start_atlas_dynamo_oathkeeper_convo01_06.mp3":{"previous_count":4,"current_count":5,"delta":1},"atlas_match_start_atlas_dynamo_oathkeeper_convo02_01.mp3":{"previous_count":2,"current_count":3,"delta":1},"atlas_match_start_atlas_dynamo_oathkeeper_convo02_03.mp3":{"previous_count":2,"current_count":3,"delta":1},"atlas_ping_careful_warden_01.mp3":{"previous_count":0,"current_count":1,"delta":1},"atlas_ping_careful_warden_02.mp3":{"previous_count":0,"current_count":1,"delta":1},"atlas_ping_careful_warden_03.mp3":{"previous_count":0,"current_count":1,"delta":1},"atlas_ping_saw_warden.mp3":{"previous_count":0,"current_count":1,"delta":1},"atlas_ping_see_warden_01.mp3":{"previous_count":0,"current_count":1,"delta":1},"atlas_ping_see_warden_02.mp3":{"previous_count":0,"current_count":1,"delta":1},"atlas_ping_warden_check_items.mp3":{"previous_count":0,"current_count":1,"delta":1},"atlas_ping_with_warden.mp3":{"previous_count":0,"current_count":1,"delta":1},"atlas_select_01.mp3":{"previous_count":3,"current_count":4,"delta":1},"atlas_select_08.mp3":{"previous_count":0,"current_count":1,"delta":1},"atlas_select_10.mp3":{"previous_count":0,"current_count":1,"delta":1},"atlas_upgrade_power1_07.mp3":{"previous_count":0,"current_count":1,"delta":1},"atlas_upgrade_power2_01.mp3":{"previous_count":0,"current_count":1,"delta":1},"atlas_upgrade_power2_02.mp3":{"previous_count":0,"current_count":1,"delta":1},"atlas_upgrade_power2_06.mp3":{"previous_count":0,"current_count":1,"delta":1},"atlas_upgrade_power3_01.mp3":{"previous_count":1,"current_count":2,"delta":1},"atlas_upgrade_power3_06.mp3":{"previous_count":0,"current_count":1,"delta":1},"atlas_upgrade_power3_09.mp3":{"previous_count":0,"current_count":1,"delta":1},"atlas_upgrade_power4_01.mp3":{"previous_count":1,"current_count":2,"delta":1},"bebop_ally_warden_killed_in_lane_01.mp3":{"previous_count":1,"current_count":2,"delta":1},"bebop_kill_warden_02.mp3":{"previous_count":1,"current_count":2,"delta":1},"bebop_kill_warden_03.mp3":{"previous_count":0,"current_count":1,"delta":1},"boho_ally_warden_killed_in_lane_01.mp3":{"previous_count":2,"current_count":3,"delta":1},"bookworm_desperation_power3_05.mp3":{"previous_count":3,"current_count":4,"delta":1},"bookworm_desperation_power4_02.mp3":{"previous_count":5,"current_count":6,"delta":1},"bookworm_desperation_power4_03.mp3":{"previous_count":4,"current_count":5,"delta":1},"bookworm_desperation_power4_05.mp3":{"previous_count":4,"current_count":5,"delta":1},"bookworm_kill_warden_01.mp3":{"previous_count":0,"current_count":1,"delta":1},"bookworm_kill_warden_02.mp3":{"previous_count":1,"current_count":2,"delta":1},"bookworm_kill_warden_03.mp3":{"previous_count":1,"current_count":2,"delta":1},"bookworm_kill_warden_04.mp3":{"previous_count":1,"current_count":2,"delta":1},"bookworm_kill_warden_05.mp3":{"previous_count":1,"current_count":2,"delta":1},"chrono_desperation_power1_03.mp3":{"previous_count":1,"current_count":2,"delta":1},"chrono_desperation_power2_01.mp3":{"previous_count":1,"current_count":2,"delta":1},"chrono_desperation_power2_04.mp3":{"previous_count":1,"current_count":2,"delta":1},"chrono_desperation_power3_03.mp3":{"previous_count":1,"current_count":2,"delta":1},"chrono_kill_warden_01.mp3":{"previous_count":0,"current_count":1,"delta":1},"doorman_ally_warden_big_ult_02.mp3":{"previous_count":2,"current_count":3,"delta":1},"doorman_ally_warden_pass_on_zipline_01.mp3":{"previous_count":2,"current_count":3,"delta":1},"doorman_enemy_warden_see_ult_01.mp3":{"previous_count":1,"current_count":2,"delta":1},"doorman_enemy_warden_see_ult_02.mp3":{"previous_count":1,"current_count":2,"delta":1},"doorman_enemy_warden_see_ult_03.mp3":{"previous_count":1,"current_count":2,"delta":1},"doorman_kill_warden_01.mp3":{"previous_count":2,"current_count":3,"delta":1},"doorman_kill_warden_02.mp3":{"previous_count":2,"current_count":3,"delta":1},"doorman_kill_warden_03.mp3":{"previous_count":2,"current_count":3,"delta":1},"doorman_kill_warden_04.mp3":{"previous_count":0,"current_count":1,"delta":1},"doorman_power4_on_magician_savannah.mp3":{"previous_count":3,"current_count":4,"delta":1},"doorman_power4_on_warden.mp3":{"previous_count":5,"current_count":6,"delta":1},"drifter_kill_warden_01.mp3":{"previous_count":2,"current_count":3,"delta":1},"drifter_kill_warden_02.mp3":{"previous_count":1,"current_count":2,"delta":1},"drifter_kill_warden_04.mp3":{"previous_count":1,"current_count":2,"delta":1},"drifter_match_start_drifter_mirage_convo03_03.mp3":{"previous_count":9,"current_count":10,"delta":1},"drifter_match_start_drifter_tengu_convo03_01.mp3":{"previous_count":36,"current_count":37,"delta":1},"dynamo_enemy_warden_see_ult_01.mp3":{"previous_count":1,"current_count":2,"delta":1},"dynamo_kill_warden_02.mp3":{"previous_count":0,"current_count":1,"delta":1},"dynamo_kill_warden_04.mp3":{"previous_count":0,"current_count":1,"delta":1},"dynamo_kill_warden_05.mp3":{"previous_count":1,"current_count":2,"delta":1},"dynamo_match_start_atlas_dynamo_oathkeeper_convo01_01.mp3":{"previous_count":4,"current_count":5,"delta":1},"dynamo_match_start_atlas_dynamo_oathkeeper_convo01_03.mp3":{"previous_count":4,"current_count":5,"delta":1},"dynamo_match_start_atlas_dynamo_oathkeeper_convo01_05.mp3":{"previous_count":4,"current_count":5,"delta":1},"dynamo_match_start_atlas_dynamo_oathkeeper_convo02_02.mp3":{"previous_count":4,"current_count":5,"delta":1},"dynamo_match_start_atlas_dynamo_oathkeeper_convo02_04.mp3":{"previous_count":2,"current_count":3,"delta":1},"dynamo_match_start_dynamo_warden_convo01_01.mp3":{"previous_count":0,"current_count":1,"delta":1},"dynamo_match_start_dynamo_warden_convo01_03.mp3":{"previous_count":0,"current_count":1,"delta":1},"dynamo_match_start_dynamo_warden_convo02_02.mp3":{"previous_count":2,"current_count":3,"delta":1},"dynamo_match_start_dynamo_warden_convo03_01.mp3":{"previous_count":3,"current_count":4,"delta":1},"forge_desperation_power1_02.mp3":{"previous_count":0,"current_count":1,"delta":1},"forge_desperation_power3_01.mp3":{"previous_count":1,"current_count":4,"delta":3},"forge_desperation_power3_02.mp3":{"previous_count":0,"current_count":1,"delta":1},"forge_desperation_power3_03.mp3":{"previous_count":0,"current_count":1,"delta":1},"forge_kill_warden_01.mp3":{"previous_count":1,"current_count":2,"delta":1},"forge_kill_warden_02.mp3":{"previous_count":0,"current_count":1,"delta":1},"forge_kill_warden_05.mp3":{"previous_count":1,"current_count":2,"delta":1},"frank_desperation_power3_02.mp3":{"previous_count":4,"current_count":5,"delta":1},"frank_kill_warden_01.mp3":{"previous_count":0,"current_count":1,"delta":1},"frank_kill_warden_05.mp3":{"previous_count":0,"current_count":1,"delta":1},"ghost_desperation_power1_05.mp3":{"previous_count":2,"current_count":3,"delta":1},"ghost_desperation_power4_02.mp3":{"previous_count":3,"current_count":4,"delta":1},"ghost_enemy_warden_see_ult_02.mp3":{"previous_count":0,"current_count":1,"delta":1},"ghost_kill_warden_03.mp3":{"previous_count":1,"current_count":2,"delta":1},"ghost_kill_warden_04.mp3":{"previous_count":1,"current_count":2,"delta":1},"gigawatt_desperation_power1_01.mp3":{"previous_count":0,"current_count":1,"delta":1},"gigawatt_desperation_power2_01.mp3":{"previous_count":0,"current_count":1,"delta":1},"gigawatt_desperation_power2_04.mp3":{"previous_count":0,"current_count":1,"delta":1},"gigawatt_kill_warden_01.mp3":{"previous_count":0,"current_count":1,"delta":1},"gigawatt_kill_warden_03.mp3":{"previous_count":0,"current_count":1,"delta":1},"gigawatt_kill_warden_04.mp3":{"previous_count":0,"current_count":1,"delta":1},"gigawatt_kill_warden_05.mp3":{"previous_count":0,"current_count":1,"delta":1},"gigawatt_match_start_gigawatt_astro_convo01_01.mp3":{"previous_count":3,"current_count":4,"delta":1},"gigawatt_match_start_gigawatt_astro_convo01_03.mp3":{"previous_count":2,"current_count":3,"delta":1},"gigawatt_match_start_gigawatt_lash_convo03_07.mp3":{"previous_count":4,"current_count":5,"delta":1},"haze_ally_warden_big_ult_01.mp3":{"previous_count":2,"current_count":3,"delta":1},"haze_desperation_power1_03.mp3":{"previous_count":0,"current_count":1,"delta":1},"haze_desperation_power2_05.mp3":{"previous_count":0,"current_count":1,"delta":1},"haze_desperation_power4_01.mp3":{"previous_count":0,"current_count":1,"delta":1},"haze_desperation_power4_05.mp3":{"previous_count":0,"current_count":1,"delta":1},"haze_kill_warden_01.mp3":{"previous_count":1,"current_count":2,"delta":1},"haze_match_start_haze_warden_convo01_01.mp3":{"previous_count":2,"current_count":3,"delta":1},"haze_match_start_haze_warden_convo01_03.mp3":{"previous_count":0,"current_count":1,"delta":1},"haze_match_start_haze_warden_convo02_02.mp3":{"previous_count":0,"current_count":1,"delta":1},"haze_match_start_haze_warden_convo02_04.mp3":{"previous_count":1,"current_count":2,"delta":1},"hornet_kill_warden_01.mp3":{"previous_count":0,"current_count":1,"delta":1},"hornet_kill_warden_04.mp3":{"previous_count":0,"current_count":1,"delta":1},"inferno_kill_warden_04.mp3":{"previous_count":0,"current_count":1,"delta":1},"inferno_kill_warden_05.mp3":{"previous_count":1,"current_count":2,"delta":1},"kelvin_desperation_power3_05.mp3":{"previous_count":1,"current_count":2,"delta":1},"kelvin_desperation_power4_01.mp3":{"previous_count":1,"current_count":2,"delta":1},"kelvin_kill_warden_01.mp3":{"previous_count":0,"current_count":1,"delta":1},"kelvin_kill_warden_02.mp3":{"previous_count":2,"current_count":3,"delta":1},"krill_desperation_power3_02.mp3":{"previous_count":0,"current_count":1,"delta":1},"krill_desperation_power3_05.mp3":{"previous_count":0,"current_count":1,"delta":1},"krill_desperation_power4_01.mp3":{"previous_count":0,"current_count":1,"delta":1},"krill_desperation_power4_04.mp3":{"previous_count":0,"current_count":1,"delta":1},"krill_desperation_power4_05.mp3":{"previous_count":0,"current_count":1,"delta":1},"krill_kill_warden_03.mp3":{"previous_count":0,"current_count":1,"delta":1},"lash_desperation_power2_04.mp3":{"previous_count":3,"current_count":4,"delta":1},"lash_desperation_power2_05.mp3":{"previous_count":3,"current_count":4,"delta":1},"lash_desperation_power4_01.mp3":{"previous_count":3,"current_count":4,"delta":1},"lash_desperation_power4_05.mp3":{"previous_count":7,"current_count":8,"delta":1},"lash_kill_warden_02.mp3":{"previous_count":2,"current_count":3,"delta":1},"lash_kill_warden_03.mp3":{"previous_count":2,"current_count":3,"delta":1},"lash_use_power4_01.mp3":{"previous_count":7,"current_count":8,"delta":1},"lash_use_power4_05.mp3":{"previous_count":5,"current_count":6,"delta":1},"mirage_desperation_power1_05.mp3":{"previous_count":3,"current_count":4,"delta":1},"mirage_desperation_power3_04.mp3":{"previous_count":2,"current_count":3,"delta":1},"mirage_desperation_power4_04.mp3":{"previous_count":3,"current_count":4,"delta":1},"mirage_kill_warden_01.mp3":{"previous_count":1,"current_count":2,"delta":1},"mirage_kill_warden_03.mp3":{"previous_count":1,"current_count":2,"delta":1},"mirage_kill_warden_04_alt_01.mp3":{"previous_count":1,"current_count":2,"delta":1},"mirage_kill_warden_04.mp3":{"previous_count":1,"current_count":2,"delta":1},"mirage_kill_warden_05.mp3":{"previous_count":1,"current_count":2,"delta":1},"mirage_match_start_drifter_mirage_convo03_04.mp3":{"previous_count":9,"current_count":10,"delta":1},"mirage_use_power2_07.mp3":{"previous_count":1,"current_count":2,"delta":1},"nano_ally_warden_big_ult_02.mp3":{"previous_count":2,"current_count":3,"delta":1},"nano_kill_warden_01.mp3":{"previous_count":1,"current_count":2,"delta":1},"nano_kill_warden_02.mp3":{"previous_count":0,"current_count":1,"delta":1},"nano_kill_warden_04.mp3":{"previous_count":1,"current_count":2,"delta":1},"newscaster_seasonal_warden_unlock_01_alt_01.mp3":{"previous_count":2,"current_count":3,"delta":1},"orion_ally_warden_big_ult_01.mp3":{"previous_count":1,"current_count":2,"delta":1},"orion_kill_warden_02.mp3":{"previous_count":1,"current_count":2,"delta":1},"orion_kill_warden_03.mp3":{"previous_count":1,"current_count":2,"delta":1},"orion_kill_warden_04.mp3":{"previous_count":0,"current_count":1,"delta":1},"orion_match_start_orion_warden_convo02_02.mp3":{"previous_count":0,"current_count":1,"delta":1},"orion_match_start_orion_warden_convo02_04.mp3":{"previous_count":0,"current_count":1,"delta":1},"orion_match_start_orion_warden_convo03_01.mp3":{"previous_count":0,"current_count":1,"delta":1},"patron_female_ally_warden_killing_streak_01.mp3":{"previous_count":1,"current_count":2,"delta":1},"patron_female_ally_warden_start_01.mp3":{"previous_count":3,"current_count":4,"delta":1},"patron_female_ally_warden_start_02.mp3":{"previous_count":3,"current_count":4,"delta":1},"patron_female_ally_warden_start_03.mp3":{"previous_count":2,"current_count":3,"delta":1},"patron_female_bespoke_enemy_update_warden.mp3":{"previous_count":4,"current_count":5,"delta":1},"patron_female_enemy_warden_killing_streak_high_01.mp3":{"previous_count":1,"current_count":2,"delta":1},"patron_female_enemy_warden_killing_streak_low_01.mp3":{"previous_count":0,"current_count":1,"delta":1},"patron_female_enemy_warden_killing_streak_medium_01.mp3":{"previous_count":0,"current_count":1,"delta":1},"patron_male_ally_warden_start_01.mp3":{"previous_count":4,"current_count":5,"delta":1},"patron_male_ally_warden_start_02.mp3":{"previous_count":4,"current_count":5,"delta":1},"patron_male_ally_warden_start_03.mp3":{"previous_count":5,"current_count":6,"delta":1},"patron_male_ally_warden_start_04.mp3":{"previous_count":4,"current_count":5,"delta":1},"patron_male_ally_warden_start_05.mp3":{"previous_count":5,"current_count":6,"delta":1},"priest_ping_attack_warden.mp3":{"previous_count":1,"current_count":2,"delta":1},"priest_ping_careful_warden_01.mp3":{"previous_count":0,"current_count":1,"delta":1},"priest_ping_careful_warden_02.mp3":{"previous_count":0,"current_count":1,"delta":1},"priest_ping_careful_warden_03.mp3":{"previous_count":1,"current_count":2,"delta":1},"punkgoat_ally_warden_big_ult_01.mp3":{"previous_count":2,"current_count":3,"delta":1},"punkgoat_ally_warden_big_ult_02.mp3":{"previous_count":1,"current_count":2,"delta":1},"punkgoat_ally_warden_big_ult_03.mp3":{"previous_count":2,"current_count":3,"delta":1},"punkgoat_ally_warden_killed_in_lane_01.mp3":{"previous_count":1,"current_count":2,"delta":1},"punkgoat_enemy_warden_see_ult_01.mp3":{"previous_count":1,"current_count":2,"delta":1},"punkgoat_enemy_warden_see_ult_02.mp3":{"previous_count":1,"current_count":2,"delta":1},"punkgoat_enemy_warden_see_ult_03.mp3":{"previous_count":0,"current_count":1,"delta":1},"shiv_kill_warden_02.mp3":{"previous_count":1,"current_count":2,"delta":1},"shiv_kill_warden_04.mp3":{"previous_count":1,"current_count":2,"delta":1},"shopkeeper_hotdog_t4_warden_01.mp3":{"previous_count":2,"current_count":3,"delta":1},"shopkeeper_hotdog_t4_warden_02.mp3":{"previous_count":1,"current_count":2,"delta":1},"shopkeeper_hotdog_t4_warden_03.mp3":{"previous_count":3,"current_count":4,"delta":1},"synth_desperation_power3_05.mp3":{"previous_count":3,"current_count":4,"delta":1},"synth_desperation_power4_01.mp3":{"previous_count":5,"current_count":6,"delta":1},"synth_kill_warden_01.mp3":{"previous_count":0,"current_count":1,"delta":1},"synth_kill_warden_02.mp3":{"previous_count":0,"current_count":1,"delta":1},"synth_use_power3_04.mp3":{"previous_count":0,"current_count":1,"delta":1},"tengu_desperation_power4_04.mp3":{"previous_count":2,"current_count":3,"delta":1},"tengu_kill_warden_01.mp3":{"previous_count":1,"current_count":2,"delta":1},"tengu_kill_warden_02.mp3":{"previous_count":1,"current_count":2,"delta":1},"tengu_kill_warden_05.mp3":{"previous_count":1,"current_count":2,"delta":1},"tengu_match_start_drifter_tengu_convo03_02.mp3":{"previous_count":15,"current_count":16,"delta":1},"tengu_use_power4_as_enemy_03.mp3":{"previous_count":1,"current_count":2,"delta":1},"tengu_use_power4_as_enemy_04.mp3":{"previous_count":1,"current_count":2,"delta":1},"vampirebat_ally_slork_killed_in_lane_01.mp3":{"previous_count":2,"current_count":3,"delta":1},"vampirebat_ally_tvspirit_killed_in_lane_01.mp3":{"previous_count":1,"current_count":2,"delta":1},"vampirebat_desperation_power2_01.mp3":{"previous_count":3,"current_count":4,"delta":1},"vampirebat_kill_magician_02.mp3":{"previous_count":0,"current_count":1,"delta":1},"vampirebat_kill_warden_01.mp3":{"previous_count":1,"current_count":2,"delta":1},"vampirebat_kill_warden_02.mp3":{"previous_count":1,"current_count":2,"delta":1},"viper_desperation_power2_01.mp3":{"previous_count":3,"current_count":4,"delta":1},"viper_desperation_power2_02.mp3":{"previous_count":1,"current_count":2,"delta":1},"viper_desperation_power4_03.mp3":{"previous_count":2,"current_count":4,"delta":2},"viper_desperation_power4_04.mp3":{"previous_count":2,"current_count":3,"delta":1},"viper_kill_warden_03.mp3":{"previous_count":0,"current_count":1,"delta":1},"viper_kill_warden_04.mp3":{"previous_count":0,"current_count":1,"delta":1},"viper_kill_warden_05.mp3":{"previous_count":0,"current_count":1,"delta":1},"viper_use_power1_02.mp3":{"previous_count":0,"current_count":1,"delta":1},"viscous_desperation_power1_02.mp3":{"previous_count":0,"current_count":1,"delta":1},"viscous_desperation_power1_04.mp3":{"previous_count":0,"current_count":1,"delta":1},"viscous_desperation_power2_01.mp3":{"previous_count":1,"current_count":2,"delta":1},"viscous_desperation_power3_02.mp3":{"previous_count":1,"current_count":2,"delta":1},"viscous_desperation_power3_04.mp3":{"previous_count":0,"current_count":1,"delta":1},"viscous_desperation_power3_05.mp3":{"previous_count":1,"current_count":2,"delta":1},"viscous_desperation_power4_01_02.mp3":{"previous_count":1,"current_count":2,"delta":1},"viscous_desperation_power4_01.mp3":{"previous_count":1,"current_count":2,"delta":1},"viscous_desperation_power4_02.mp3":{"previous_count":0,"current_count":1,"delta":1},"viscous_desperation_power4_03.mp3":{"previous_count":0,"current_count":1,"delta":1},"viscous_desperation_power4_04.mp3":{"previous_count":1,"current_count":2,"delta":1},"viscous_desperation_power4_05_02.mp3":{"previous_count":0,"current_count":1,"delta":1},"viscous_desperation_power4_05.mp3":{"previous_count":0,"current_count":1,"delta":1},"viscous_desperation_power4_06.mp3":{"previous_count":1,"current_count":2,"delta":1},"viscous_desperation_power4_07.mp3":{"previous_count":0,"current_count":1,"delta":1},"viscous_desperation_power4_09.mp3":{"previous_count":0,"current_count":1,"delta":1},"viscous_kill_warden_01.mp3":{"previous_count":0,"current_count":1,"delta":1},"viscous_kill_warden_02.mp3":{"previous_count":0,"current_count":1,"delta":1},"viscous_kill_warden_05.mp3":{"previous_count":0,"current_count":2,"delta":2},"warden_close_call_01.mp3":{"previous_count":0,"current_count":1,"delta":1},"warden_close_call_03.mp3":{"previous_count":0,"current_count":1,"delta":1},"warden_close_call_04.mp3":{"previous_count":0,"current_count":1,"delta":1},"warden_close_call_05.mp3":{"previous_count":0,"current_count":1,"delta":1},"warden_desperation_power1_01.mp3":{"previous_count":1,"current_count":2,"delta":1},"warden_desperation_power1_02.mp3":{"previous_count":0,"current_count":1,"delta":1},"warden_desperation_power1_03.mp3":{"previous_count":0,"current_count":1,"delta":1},"warden_desperation_power1_05.mp3":{"previous_count":0,"current_count":1,"delta":1},"warden_desperation_power2_01.mp3":{"previous_count":2,"current_count":3,"delta":1},"warden_desperation_power2_02.mp3":{"previous_count":1,"current_count":2,"delta":1},"warden_desperation_power2_03.mp3":{"previous_count":2,"current_count":3,"delta":1},"warden_desperation_power2_04.mp3":{"previous_count":1,"current_count":2,"delta":1},"warden_desperation_power3_01.mp3":{"previous_count":2,"current_count":3,"delta":1},"warden_desperation_power3_02.mp3":{"previous_count":1,"current_count":2,"delta":1},"warden_desperation_power3_03.mp3":{"previous_count":1,"current_count":3,"delta":2},"warden_desperation_power3_04.mp3":{"previous_count":2,"current_count":3,"delta":1},"warden_desperation_power4_01.mp3":{"previous_count":4,"current_count":5,"delta":1},"warden_desperation_power4_02.mp3":{"previous_count":3,"current_count":4,"delta":1},"warden_desperation_power4_03.mp3":{"previous_count":3,"current_count":4,"delta":1},"warden_desperation_power4_04.mp3":{"previous_count":4,"current_count":6,"delta":2},"warden_hunt_01.mp3":{"previous_count":0,"current_count":1,"delta":1},"warden_hunt_02.mp3":{"previous_count":0,"current_count":1,"delta":1},"warden_interrupt_01.mp3":{"previous_count":0,"current_count":1,"delta":1},"warden_interrupt_03.mp3":{"previous_count":0,"current_count":1,"delta":1},"warden_interrupt_04.mp3":{"previous_count":0,"current_count":1,"delta":1},"warden_interrupt_05.mp3":{"previous_count":0,"current_count":1,"delta":1},"warden_kill_anyhero_01.mp3":{"previous_count":1,"current_count":2,"delta":1},"warden_killstreak_high_01.mp3":{"previous_count":2,"current_count":3,"delta":1},"warden_killstreak_high_02.mp3":{"previous_count":0,"current_count":1,"delta":1},"warden_killstreak_high_03.mp3":{"previous_count":1,"current_count":2,"delta":1},"warden_killstreak_mid_01.mp3":{"previous_count":1,"current_count":2,"delta":1},"warden_killstreak_mid_02.mp3":{"previous_count":0,"current_count":1,"delta":1},"warden_killstreak_mid_03.mp3":{"previous_count":1,"current_count":2,"delta":1},"warden_killstreak_start_01.mp3":{"previous_count":1,"current_count":2,"delta":1},"warden_killstreak_start_02.mp3":{"previous_count":0,"current_count":1,"delta":1},"warden_killstreak_start_03.mp3":{"previous_count":1,"current_count":2,"delta":1},"warden_killstreak_start_04.mp3":{"previous_count":1,"current_count":2,"delta":1},"warden_last_one_standing_01.mp3":{"previous_count":1,"current_count":2,"delta":1},"warden_last_one_standing_02.mp3":{"previous_count":1,"current_count":2,"delta":1},"warden_leave_base_03.mp3":{"previous_count":0,"current_count":1,"delta":1},"warden_leave_base_04.mp3":{"previous_count":0,"current_count":1,"delta":1},"warden_leave_base_05.mp3":{"previous_count":0,"current_count":1,"delta":1},"warden_low_health_warning.mp3":{"previous_count":1,"current_count":2,"delta":1},"warden_melee_kill_01.mp3":{"previous_count":1,"current_count":2,"delta":1},"warden_melee_kill_02.mp3":{"previous_count":0,"current_count":1,"delta":1},"warden_melee_kill_03.mp3":{"previous_count":1,"current_count":2,"delta":1},"warden_melee_kill_04.mp3":{"previous_count":1,"current_count":2,"delta":1},"warden_melee_kill_05.mp3":{"previous_count":0,"current_count":1,"delta":1},"warden_near_miss_04.mp3":{"previous_count":0,"current_count":1,"delta":1},"warden_outnumbered_01.mp3":{"previous_count":1,"current_count":2,"delta":1},"warden_parry_01.mp3":{"previous_count":1,"current_count":2,"delta":1},"warden_parry_02.mp3":{"previous_count":0,"current_count":1,"delta":1},"warden_pick_up_gold_02.mp3":{"previous_count":0,"current_count":1,"delta":1},"warden_pick_up_gold_03.mp3":{"previous_count":0,"current_count":4,"delta":4},"warden_pick_up_gold_04.mp3":{"previous_count":0,"current_count":1,"delta":1},"warden_pick_up_gold_05.mp3":{"previous_count":0,"current_count":1,"delta":1},"warden_ping_post_game_02.mp3":{"previous_count":1,"current_count":2,"delta":1},"warden_ping_pre_game_01.mp3":{"previous_count":2,"current_count":3,"delta":1},"warden_ping_pre_game_02.mp3":{"previous_count":1,"current_count":2,"delta":1},"warden_ping_pre_game_06.mp3":{"previous_count":1,"current_count":2,"delta":1},"warden_revenge_kill.mp3":{"previous_count":0,"current_count":1,"delta":1},"warden_select_01.mp3":{"previous_count":1,"current_count":2,"delta":1},"warden_select_04.mp3":{"previous_count":0,"current_count":1,"delta":1},"warden_select_05.mp3":{"previous_count":0,"current_count":1,"delta":1},"warden_select_06.mp3":{"previous_count":0,"current_count":1,"delta":1},"warden_select_07.mp3":{"previous_count":0,"current_count":1,"delta":1},"warden_select_08.mp3":{"previous_count":1,"current_count":2,"delta":1},"warden_select_09.mp3":{"previous_count":0,"current_count":1,"delta":1},"warden_unselect_03.mp3":{"previous_count":0,"current_count":1,"delta":1},"warden_unselect_05.mp3":{"previous_count":0,"current_count":1,"delta":1},"warden_unselect_07.mp3":{"previous_count":2,"current_count":3,"delta":1},"warden_unselect_08.mp3":{"previous_count":0,"current_count":1,"delta":1},"warden_upgrade_power1_01.mp3":{"previous_count":1,"current_count":2,"delta":1},"warden_upgrade_power1_03.mp3":{"previous_count":0,"current_count":1,"delta":1},"warden_upgrade_power1_04.mp3":{"previous_count":0,"current_count":1,"delta":1},"warden_upgrade_power1_08.mp3":{"previous_count":1,"current_count":2,"delta":1},"warden_upgrade_power2_01.mp3":{"previous_count":1,"current_count":2,"delta":1},"warden_upgrade_power2_07.mp3":{"previous_count":0,"current_count":1,"delta":1},"warden_upgrade_power2_10.mp3":{"previous_count":1,"current_count":2,"delta":1},"warden_upgrade_power3_01.mp3":{"previous_count":1,"current_count":2,"delta":1},"warden_upgrade_power3_04.mp3":{"previous_count":0,"current_count":1,"delta":1},"warden_upgrade_power4_01.mp3":{"previous_count":2,"current_count":3,"delta":1},"warden_upgrade_power4_02.mp3":{"previous_count":0,"current_count":1,"delta":1},"warden_upgrade_power4_08.mp3":{"previous_count":0,"current_count":1,"delta":1},"warden_upgrade_power4_09.mp3":{"previous_count":0,"current_count":1,"delta":1},"warden_use_power1_03.mp3":{"previous_count":1,"current_count":2,"delta":1},"warden_use_power1_04.mp3":{"previous_count":3,"current_count":5,"delta":2},"warden_use_power1_06.mp3":{"previous_count":2,"current_count":3,"delta":1},"warden_use_power1_08.mp3":{"previous_count":2,"current_count":3,"delta":1},"warden_use_power1_09.mp3":{"previous_count":1,"current_count":2,"delta":1},"warden_use_power1_10.mp3":{"previous_count":2,"current_count":3,"delta":1},"warden_use_power2_01.mp3":{"previous_count":2,"current_count":3,"delta":1},"warden_use_power2_03.mp3":{"previous_count":1,"current_count":2,"delta":1},"warden_use_power2_05.mp3":{"previous_count":1,"current_count":2,"delta":1},"warden_use_power2_09.mp3":{"previous_count":2,"current_count":3,"delta":1},"warden_use_power2_10.mp3":{"previous_count":2,"current_count":3,"delta":1},"warden_use_power3_01.mp3":{"previous_count":3,"current_count":4,"delta":1},"warden_use_power3_02.mp3":{"previous_count":1,"current_count":2,"delta":1},"warden_use_power3_03.mp3":{"previous_count":1,"current_count":2,"delta":1},"warden_use_power3_04.mp3":{"previous_count":2,"current_count":3,"delta":1},"warden_use_power3_06.mp3":{"previous_count":2,"current_count":3,"delta":1},"warden_use_power3_07.mp3":{"previous_count":3,"current_count":5,"delta":2},"warden_use_power3_08.mp3":{"previous_count":3,"current_count":4,"delta":1},"warden_use_power4_01.mp3":{"previous_count":2,"current_count":3,"delta":1},"warden_use_power4_04.mp3":{"previous_count":2,"current_count":3,"delta":1},"warden_use_power4_06.mp3":{"previous_count":2,"current_count":3,"delta":1},"warden_use_power4_07.mp3":{"previous_count":3,"current_count":4,"delta":1},"warden_use_power4_08.mp3":{"previous_count":2,"current_count":3,"delta":1},"warden_use_power4_09.mp3":{"previous_count":2,"current_count":3,"delta":1},"warden_use_power4_10.mp3":{"previous_count":2,"current_count":3,"delta":1},"wraith_desperation_power4_05.mp3":{"previous_count":0,"current_count":1,"delta":1},"wraith_kill_warden_01.mp3":{"previous_count":0,"current_count":1,"delta":1},"yamato_desperation_power1_02.mp3":{"previous_count":2,"current_count":3,"delta":1},"yamato_desperation_power1_03.mp3":{"previous_count":1,"current_count":2,"delta":1},"yamato_desperation_power1_04.mp3":{"previous_count":1,"current_count":2,"delta":1},"yamato_desperation_power1_05.mp3":{"previous_count":1,"current_count":2,"delta":1},"yamato_desperation_power4_02.mp3":{"previous_count":2,"current_count":3,"delta":1},"yamato_desperation_power4_04.mp3":{"previous_count":2,"current_count":3,"delta":1},"yamato_desperation_power4_05.mp3":{"previous_count":0,"current_count":1,"delta":1},"yamato_kill_warden_01.mp3":{"previous_count":2,"current_count":3,"delta":1},"yamato_kill_warden_05.mp3":{"previous_count":1,"current_count":2,"delta":1}},"conversations":{"abrams_dynamo_convo01_oathkeeper":{"previous_count":4,"current_count":5,"delta":1},"abrams_dynamo_convo02_oathkeeper":{"previous_count":3,"current_count":4,"delta":1},"drifter_ivy_convo03":{"previous_count":33,"current_count":34,"delta":1},"drifter_mirage_convo03":{"previous_count":10,"current_count":11,"delta":1},"dynamo_warden_convo01":{"previous_count":0,"current_count":1,"delta":1},"dynamo_warden_convo02":{"previous_count":2,"current_count":3,"delta":1},"dynamo_warden_convo03":{"previous_count":3,"current_count":4,"delta":1},"grey talon_warden_convo02":{"previous_count":0,"current_count":1,"delta":1},"grey talon_warden_convo03":{"previous_count":0,"current_count":1,"delta":1},"haze_warden_convo01":{"previous_count":2,"current_count":3,"delta":1},"haze_warden_convo02":{"previous_count":1,"current_count":2,"delta":1},"holliday_seven_convo01":{"previous_count":3,"current_count":4,"delta":1},"lash_seven_convo03":{"previous_count":4,"current_count":5,"delta":1}},"character_totals":{"abrams":{"previous_count":303,"current_count":321,"delta":18},"bebop":{"previous_count":275,"current_count":278,"delta":3},"billy":{"previous_count":221,"current_count":228,"delta":7},"boho":{"previous_count":88,"current_count":89,"delta":1},"calico":{"previous_count":139,"current_count":143,"delta":4},"doorman":{"previous_count":298,"current_count":309,"delta":11},"drifter":{"previous_count":188,"current_count":191,"delta":3},"dynamo":{"previous_count":122,"current_count":126,"delta":4},"fathom":{"previous_count":54,"current_count":55,"delta":1},"grey talon":{"previous_count":167,"current_count":171,"delta":4},"haze":{"previous_count":189,"current_count":191,"delta":2},"holliday":{"previous_count":169,"current_count":171,"delta":2},"infernus":{"previous_count":105,"current_count":107,"delta":2},"ivy":{"previous_count":137,"current_count":140,"delta":3},"kelvin":{"previous_count":91,"current_count":93,"delta":2},"krill":{"previous_count":136,"current_count":137,"delta":1},"lady geist":{"previous_count":114,"current_count":117,"delta":3},"lash":{"previous_count":211,"current_count":213,"delta":2},"magician":{"previous_count":36,"current_count":37,"delta":1},"mcginnis":{"previous_count":88,"current_count":91,"delta":3},"mina":{"previous_count":206,"current_count":208,"delta":2},"mirage":{"previous_count":123,"current_count":128,"delta":5},"newscaster":{"previous_count":8,"current_count":9,"delta":1},"paige":{"previous_count":142,"current_count":147,"delta":5},"paradox":{"previous_count":91,"current_count":92,"delta":1},"patron female":{"previous_count":144,"current_count":152,"delta":8},"patron male":{"previous_count":86,"current_count":91,"delta":5},"pocket":{"previous_count":246,"current_count":248,"delta":2},"priest":{"previous_count":202,"current_count":206,"delta":4},"seven":{"previous_count":161,"current_count":165,"delta":4},"shiv":{"previous_count":194,"current_count":196,"delta":2},"shopkeeper_hotdog":{"previous_count":22,"current_count":25,"delta":3},"victor":{"previous_count":152,"current_count":154,"delta":2},"vindicta":{"previous_count":105,"current_count":107,"delta":2},"viper":{"previous_count":181,"current_count":184,"delta":3},"viscous":{"previous_count":168,"current_count":172,"delta":4},"wraith":{"previous_count":98,"current_count":99,"delta":1},"yamato":{"previous_count":147,"current_count":149,"delta":2}}}}}