{"version_info":{"id":19,"version_hash":"4445e789","version_folder":"Games/Deadlock/DeadlockAugust22025","created_at":"2025-09-16T03:50:05.663748+00:00"},"export_timestamp":"2025-10-02T13:37:36.313Z","delta":{"isFirstExport":false,"changes":{"voicelines":{"astro_ally_gigawatt_multi_kill_ult_01.mp3":{"previous_count":1,"current_count":2,"delta":1},"astro_ally_gigawatt_multi_kill_ult_02.mp3":{"previous_count":0,"current_count":1,"delta":1},"astro_ally_gigawatt_multi_kill_ult_03.mp3":{"previous_count":0,"current_count":1,"delta":1},"astro_ally_lash_see_massive_stomp_01.mp3":{"previous_count":2,"current_count":3,"delta":1},"astro_ally_lash_see_massive_stomp_02.mp3":{"previous_count":2,"current_count":3,"delta":1},"astro_ally_lash_see_massive_stomp_03.mp3":{"previous_count":3,"current_count":4,"delta":1},"astro_enemy_lash_mid_air_kill_01.mp3":{"previous_count":3,"current_count":4,"delta":1},"astro_enemy_lash_mid_air_kill_02.mp3":{"previous_count":1,"current_count":2,"delta":1},"astro_enemy_lash_mid_air_kill_03.mp3":{"previous_count":3,"current_count":4,"delta":1},"atlas_ally_gigawatt_multi_kill_ult_01.mp3":{"previous_count":1,"current_count":2,"delta":1},"atlas_ally_gigawatt_multi_kill_ult_02.mp3":{"previous_count":1,"current_count":2,"delta":1},"atlas_ally_gigawatt_multi_kill_ult_03.mp3":{"previous_count":1,"current_count":2,"delta":1},"atlas_ally_lash_see_massive_stomp_01.mp3":{"previous_count":2,"current_count":3,"delta":1},"atlas_ally_lash_see_massive_stomp_02.mp3":{"previous_count":1,"current_count":2,"delta":1},"atlas_ally_lash_see_massive_stomp_03.mp3":{"previous_count":0,"current_count":1,"delta":1},"atlas_enemy_lash_mid_air_kill_01.mp3":{"previous_count":2,"current_count":3,"delta":1},"atlas_enemy_lash_mid_air_kill_02.mp3":{"previous_count":2,"current_count":3,"delta":1},"atlas_enemy_lash_mid_air_kill_03.mp3":{"previous_count":2,"current_count":3,"delta":1},"atlas_killstreak_high_01.mp3":{"previous_count":4,"current_count":5,"delta":1},"atlas_killstreak_high_02.mp3":{"previous_count":4,"current_count":5,"delta":1},"atlas_killstreak_high_03.mp3":{"previous_count":7,"current_count":8,"delta":1},"atlas_killstreak_mid_01.mp3":{"previous_count":4,"current_count":5,"delta":1},"atlas_killstreak_mid_02.mp3":{"previous_count":2,"current_count":3,"delta":1},"atlas_killstreak_mid_03.mp3":{"previous_count":4,"current_count":5,"delta":1},"atlas_killstreak_start_01.mp3":{"previous_count":5,"current_count":6,"delta":1},"atlas_killstreak_start_02.mp3":{"previous_count":4,"current_count":5,"delta":1},"atlas_killstreak_start_03.mp3":{"previous_count":4,"current_count":5,"delta":1},"bebop_ally_lash_killed_in_lane_01.mp3":{"previous_count":5,"current_count":6,"delta":1},"bebop_ally_lash_killed_in_lane_02.mp3":{"previous_count":8,"current_count":9,"delta":1},"bebop_kill_gigawatt_03.mp3":{"previous_count":0,"current_count":1,"delta":1},"bebop_killstreak_high_01.mp3":{"previous_count":4,"current_count":5,"delta":1},"bebop_killstreak_high_02.mp3":{"previous_count":4,"current_count":5,"delta":1},"bebop_killstreak_high_03.mp3":{"previous_count":4,"current_count":5,"delta":1},"bebop_killstreak_mid_01.mp3":{"previous_count":3,"current_count":4,"delta":1},"doorman_ally_gigawatt_multi_kill_ult_01.mp3":{"previous_count":3,"current_count":4,"delta":1},"doorman_ally_gigawatt_multi_kill_ult_02.mp3":{"previous_count":1,"current_count":2,"delta":1},"doorman_ally_gigawatt_multi_kill_ult_03.mp3":{"previous_count":3,"current_count":4,"delta":1},"doorman_ally_lash_see_massive_stomp_01.mp3":{"previous_count":3,"current_count":4,"delta":1},"doorman_ally_lash_see_massive_stomp_02.mp3":{"previous_count":4,"current_count":5,"delta":1},"doorman_ally_lash_see_massive_stomp_03.mp3":{"previous_count":3,"current_count":4,"delta":1},"doorman_enemy_lash_mid_air_kill_01.mp3":{"previous_count":3,"current_count":4,"delta":1},"doorman_enemy_lash_mid_air_kill_02.mp3":{"previous_count":2,"current_count":3,"delta":1},"doorman_enemy_lash_mid_air_kill_03.mp3":{"previous_count":3,"current_count":4,"delta":1},"drifter_ally_lash_killed_in_lane_01.mp3":{"previous_count":2,"current_count":3,"delta":1},"drifter_bespoke_ability_line_01.mp3":{"previous_count":8,"current_count":9,"delta":1},"drifter_bespoke_ability_line_02.mp3":{"previous_count":8,"current_count":9,"delta":1},"drifter_bespoke_ability_line_03.mp3":{"previous_count":5,"current_count":6,"delta":1},"drifter_bespoke_ability_line_04.mp3":{"previous_count":4,"current_count":5,"delta":1},"drifter_bespoke_ability_line_05.mp3":{"previous_count":4,"current_count":5,"delta":1},"drifter_bespoke_ability_line_06.mp3":{"previous_count":4,"current_count":5,"delta":1},"drifter_bespoke_ability_line_07.mp3":{"previous_count":4,"current_count":5,"delta":1},"drifter_bespoke_ability_line_08.mp3":{"previous_count":3,"current_count":4,"delta":1},"drifter_bespoke_ability_line_09.mp3":{"previous_count":3,"current_count":4,"delta":1},"drifter_bespoke_ability_line_12.mp3":{"previous_count":2,"current_count":4,"delta":2},"drifter_bespoke_ability_line_13.mp3":{"previous_count":2,"current_count":3,"delta":1},"drifter_match_start_drifter_tengu_convo03_01.mp3":{"previous_count":70,"current_count":72,"delta":2},"drifter_match_start_drifter_tengu_convo03_03.mp3":{"previous_count":31,"current_count":32,"delta":1},"drifter_select_01.mp3":{"previous_count":11,"current_count":12,"delta":1},"drifter_upgrade_power2_01.mp3":{"previous_count":1,"current_count":2,"delta":1},"drifter_upgrade_power2_02.mp3":{"previous_count":0,"current_count":1,"delta":1},"drifter_upgrade_power2_03.mp3":{"previous_count":1,"current_count":2,"delta":1},"drifter_upgrade_power2_04.mp3":{"previous_count":1,"current_count":2,"delta":1},"drifter_upgrade_power2_05.mp3":{"previous_count":1,"current_count":2,"delta":1},"drifter_upgrade_power2_06.mp3":{"previous_count":0,"current_count":1,"delta":1},"drifter_upgrade_power2_07.mp3":{"previous_count":2,"current_count":3,"delta":1},"dynamo_ally_gigawatt_multi_kill_ult_01.mp3":{"previous_count":1,"current_count":2,"delta":1},"dynamo_ally_gigawatt_multi_kill_ult_02.mp3":{"previous_count":1,"current_count":2,"delta":1},"dynamo_ally_gigawatt_multi_kill_ult_03.mp3":{"previous_count":0,"current_count":1,"delta":1},"dynamo_ally_lash_see_massive_stomp_01.mp3":{"previous_count":3,"current_count":4,"delta":1},"dynamo_ally_lash_see_massive_stomp_02.mp3":{"previous_count":2,"current_count":3,"delta":1},"dynamo_ally_lash_see_massive_stomp_03.mp3":{"previous_count":2,"current_count":3,"delta":1},"dynamo_enemy_lash_mid_air_kill_01.mp3":{"previous_count":2,"current_count":3,"delta":1},"dynamo_enemy_lash_mid_air_kill_02.mp3":{"previous_count":2,"current_count":3,"delta":1},"dynamo_enemy_lash_mid_air_kill_03.mp3":{"previous_count":2,"current_count":3,"delta":1},"frank_ally_atlas_unkillable_01.mp3":{"previous_count":1,"current_count":2,"delta":1},"frank_ally_atlas_unkillable_02.mp3":{"previous_count":1,"current_count":2,"delta":1},"frank_ally_gigawatt_multi_kill_ult_01.mp3":{"previous_count":2,"current_count":3,"delta":1},"frank_ally_gigawatt_multi_kill_ult_02.mp3":{"previous_count":1,"current_count":2,"delta":1},"frank_ally_gigawatt_multi_kill_ult_03.mp3":{"previous_count":1,"current_count":2,"delta":1},"frank_desperation_power1_01.mp3":{"previous_count":6,"current_count":8,"delta":2},"frank_desperation_power2_01.mp3":{"previous_count":4,"current_count":5,"delta":1},"frank_desperation_power2_02.mp3":{"previous_count":5,"current_count":6,"delta":1},"frank_desperation_power2_04.mp3":{"previous_count":5,"current_count":6,"delta":1},"frank_desperation_power2_05.mp3":{"previous_count":3,"current_count":4,"delta":1},"frank_desperation_power3_02.mp3":{"previous_count":5,"current_count":6,"delta":1},"frank_desperation_power3_03.mp3":{"previous_count":3,"current_count":4,"delta":1},"frank_desperation_power3_04.mp3":{"previous_count":4,"current_count":5,"delta":1},"frank_desperation_power3_05.mp3":{"previous_count":4,"current_count":5,"delta":1},"frank_kill_atlas_01.mp3":{"previous_count":2,"current_count":4,"delta":2},"frank_kill_atlas_02.mp3":{"previous_count":1,"current_count":2,"delta":1},"frank_use_power2_01.mp3":{"previous_count":7,"current_count":8,"delta":1},"frank_use_power2_02.mp3":{"previous_count":10,"current_count":11,"delta":1},"frank_use_power2_03.mp3":{"previous_count":9,"current_count":10,"delta":1},"frank_use_power2_04.mp3":{"previous_count":8,"current_count":9,"delta":1},"frank_use_power2_05.mp3":{"previous_count":7,"current_count":8,"delta":1},"frank_use_power2_06.mp3":{"previous_count":9,"current_count":10,"delta":1},"frank_use_power2_07.mp3":{"previous_count":8,"current_count":9,"delta":1},"frank_use_power2_08.mp3":{"previous_count":8,"current_count":9,"delta":1},"frank_use_power2_09.mp3":{"previous_count":9,"current_count":10,"delta":1},"frank_use_power2_10.mp3":{"previous_count":7,"current_count":8,"delta":1},"frank_use_power4_01.mp3":{"previous_count":4,"current_count":6,"delta":2},"frank_use_power4_02.mp3":{"previous_count":5,"current_count":6,"delta":1},"frank_use_power4_03.mp3":{"previous_count":4,"current_count":5,"delta":1},"frank_use_power4_04.mp3":{"previous_count":7,"current_count":8,"delta":1},"frank_use_power4_05.mp3":{"previous_count":4,"current_count":5,"delta":1},"frank_use_power4_06.mp3":{"previous_count":10,"current_count":11,"delta":1},"frank_use_power4_07.mp3":{"previous_count":4,"current_count":5,"delta":1},"ghost_ally_gigawatt_multi_kill_ult_02.mp3":{"previous_count":1,"current_count":2,"delta":1},"ghost_ally_gigawatt_multi_kill_ult_03.mp3":{"previous_count":1,"current_count":2,"delta":1},"haze_ally_gigawatt_multi_kill_ult_01.mp3":{"previous_count":1,"current_count":2,"delta":1},"haze_ally_gigawatt_multi_kill_ult_02.mp3":{"previous_count":1,"current_count":2,"delta":1},"haze_ally_gigawatt_multi_kill_ult_03.mp3":{"previous_count":1,"current_count":2,"delta":1},"haze_ally_lash_see_massive_stomp_01.mp3":{"previous_count":1,"current_count":2,"delta":1},"haze_ally_lash_see_massive_stomp_02.mp3":{"previous_count":2,"current_count":3,"delta":1},"haze_ally_lash_see_massive_stomp_03.mp3":{"previous_count":2,"current_count":3,"delta":1},"haze_desperation_power1_01.mp3":{"previous_count":1,"current_count":2,"delta":1},"haze_desperation_power1_02.mp3":{"previous_count":1,"current_count":2,"delta":1},"haze_desperation_power1_03.mp3":{"previous_count":2,"current_count":3,"delta":1},"haze_desperation_power1_04.mp3":{"previous_count":0,"current_count":1,"delta":1},"haze_desperation_power1_05.mp3":{"previous_count":0,"current_count":1,"delta":1},"haze_desperation_power2_01.mp3":{"previous_count":0,"current_count":1,"delta":1},"haze_desperation_power2_02.mp3":{"previous_count":0,"current_count":1,"delta":1},"haze_desperation_power2_03.mp3":{"previous_count":1,"current_count":2,"delta":1},"haze_desperation_power2_04.mp3":{"previous_count":0,"current_count":1,"delta":1},"haze_desperation_power2_05.mp3":{"previous_count":1,"current_count":2,"delta":1},"haze_desperation_power4_01.mp3":{"previous_count":1,"current_count":2,"delta":1},"haze_desperation_power4_02.mp3":{"previous_count":1,"current_count":2,"delta":1},"haze_desperation_power4_03.mp3":{"previous_count":2,"current_count":3,"delta":1},"haze_desperation_power4_04.mp3":{"previous_count":1,"current_count":2,"delta":1},"haze_enemy_lash_mid_air_kill_01.mp3":{"previous_count":1,"current_count":2,"delta":1},"haze_enemy_lash_mid_air_kill_02.mp3":{"previous_count":1,"current_count":2,"delta":1},"haze_enemy_lash_mid_air_kill_03.mp3":{"previous_count":1,"current_count":2,"delta":1},"haze_killstreak_high_01.mp3":{"previous_count":2,"current_count":3,"delta":1},"haze_killstreak_high_02.mp3":{"previous_count":2,"current_count":3,"delta":1},"haze_killstreak_high_03.mp3":{"previous_count":3,"current_count":4,"delta":1},"haze_use_power4_01.mp3":{"previous_count":3,"current_count":4,"delta":1},"haze_use_power4_02.mp3":{"previous_count":4,"current_count":5,"delta":1},"haze_use_power4_03.mp3":{"previous_count":3,"current_count":4,"delta":1},"haze_use_power4_05.mp3":{"previous_count":2,"current_count":3,"delta":1},"haze_use_power4_06.mp3":{"previous_count":2,"current_count":3,"delta":1},"haze_use_power4_07.mp3":{"previous_count":2,"current_count":3,"delta":1},"haze_use_power4_08.mp3":{"previous_count":3,"current_count":4,"delta":1},"haze_use_power4_10.mp3":{"previous_count":2,"current_count":3,"delta":1},"hornet_ally_drifter_killed_in_lane_01.mp3":{"previous_count":1,"current_count":2,"delta":1},"hornet_ally_orion_killed_in_lane_01.mp3":{"previous_count":3,"current_count":4,"delta":1},"hornet_kill_atlas_01.mp3":{"previous_count":2,"current_count":3,"delta":1},"hornet_kill_atlas_05.mp3":{"previous_count":3,"current_count":4,"delta":1},"hornet_kill_bebop_05.mp3":{"previous_count":1,"current_count":2,"delta":1},"hornet_kill_bookworm_01.mp3":{"previous_count":0,"current_count":1,"delta":1},"hornet_kill_bookworm_02.mp3":{"previous_count":0,"current_count":1,"delta":1},"hornet_kill_bookworm_03.mp3":{"previous_count":0,"current_count":1,"delta":1},"hornet_kill_bookworm_04.mp3":{"previous_count":0,"current_count":1,"delta":1},"hornet_kill_bookworm_05.mp3":{"previous_count":0,"current_count":1,"delta":1},"hornet_kill_doorman_01.mp3":{"previous_count":4,"current_count":5,"delta":1},"hornet_kill_doorman_02.mp3":{"previous_count":2,"current_count":3,"delta":1},"hornet_kill_doorman_05.mp3":{"previous_count":5,"current_count":6,"delta":1},"hornet_kill_drifter_01.mp3":{"previous_count":2,"current_count":3,"delta":1},"hornet_kill_drifter_02.mp3":{"previous_count":2,"current_count":3,"delta":1},"hornet_kill_drifter_03.mp3":{"previous_count":1,"current_count":2,"delta":1},"hornet_kill_drifter_04.mp3":{"previous_count":2,"current_count":3,"delta":1},"hornet_kill_drifter_05.mp3":{"previous_count":3,"current_count":4,"delta":1},"hornet_kill_dynamo_01.mp3":{"previous_count":0,"current_count":1,"delta":1},"hornet_kill_dynamo_03.mp3":{"previous_count":0,"current_count":1,"delta":1},"hornet_kill_dynamo_04.mp3":{"previous_count":0,"current_count":1,"delta":1},"hornet_kill_frank_01.mp3":{"previous_count":1,"current_count":2,"delta":1},"hornet_kill_frank_02.mp3":{"previous_count":1,"current_count":2,"delta":1},"hornet_kill_frank_03.mp3":{"previous_count":0,"current_count":1,"delta":1},"hornet_kill_frank_04.mp3":{"previous_count":0,"current_count":1,"delta":1},"hornet_kill_frank_05.mp3":{"previous_count":0,"current_count":1,"delta":1},"hornet_kill_gigawatt_01.mp3":{"previous_count":0,"current_count":1,"delta":1},"hornet_kill_gigawatt_02.mp3":{"previous_count":0,"current_count":1,"delta":1},"hornet_kill_gigawatt_04.mp3":{"previous_count":0,"current_count":1,"delta":1},"hornet_kill_inferno_01.mp3":{"previous_count":0,"current_count":1,"delta":1},"hornet_kill_inferno_02.mp3":{"previous_count":0,"current_count":1,"delta":1},"hornet_kill_inferno_03.mp3":{"previous_count":0,"current_count":1,"delta":1},"hornet_kill_inferno_04.mp3":{"previous_count":0,"current_count":1,"delta":1},"hornet_kill_krill_01.mp3":{"previous_count":0,"current_count":1,"delta":1},"hornet_kill_krill_04.mp3":{"previous_count":0,"current_count":1,"delta":1},"hornet_kill_krill_05.mp3":{"previous_count":0,"current_count":1,"delta":1},"hornet_kill_lash_01.mp3":{"previous_count":1,"current_count":2,"delta":1},"hornet_kill_lash_02.mp3":{"previous_count":1,"current_count":2,"delta":1},"hornet_kill_lash_03.mp3":{"previous_count":1,"current_count":2,"delta":1},"hornet_kill_lash_04.mp3":{"previous_count":1,"current_count":2,"delta":1},"hornet_kill_lash_05.mp3":{"previous_count":1,"current_count":2,"delta":1},"hornet_kill_mirage_02.mp3":{"previous_count":0,"current_count":1,"delta":1},"hornet_kill_mirage_03.mp3":{"previous_count":0,"current_count":1,"delta":1},"hornet_kill_mirage_05.mp3":{"previous_count":0,"current_count":1,"delta":1},"hornet_kill_orion_01.mp3":{"previous_count":1,"current_count":2,"delta":1},"hornet_kill_orion_02.mp3":{"previous_count":1,"current_count":2,"delta":1},"hornet_kill_orion_03.mp3":{"previous_count":1,"current_count":2,"delta":1},"hornet_kill_orion_04.mp3":{"previous_count":1,"current_count":2,"delta":1},"hornet_kill_orion_05.mp3":{"previous_count":2,"current_count":3,"delta":1},"hornet_kill_priest_01.mp3":{"previous_count":2,"current_count":3,"delta":1},"hornet_kill_priest_02.mp3":{"previous_count":1,"current_count":2,"delta":1},"hornet_kill_priest_03.mp3":{"previous_count":0,"current_count":1,"delta":1},"hornet_kill_priest_04.mp3":{"previous_count":0,"current_count":1,"delta":1},"hornet_kill_priest_05.mp3":{"previous_count":2,"current_count":3,"delta":1},"hornet_kill_shiv_01.mp3":{"previous_count":0,"current_count":1,"delta":1},"hornet_kill_shiv_02.mp3":{"previous_count":0,"current_count":1,"delta":1},"hornet_kill_shiv_03.mp3":{"previous_count":0,"current_count":1,"delta":1},"hornet_kill_shiv_04.mp3":{"previous_count":0,"current_count":1,"delta":1},"hornet_kill_synth_01.mp3":{"previous_count":2,"current_count":3,"delta":1},"hornet_kill_synth_02.mp3":{"previous_count":2,"current_count":3,"delta":1},"hornet_kill_synth_03.mp3":{"previous_count":1,"current_count":2,"delta":1},"hornet_kill_synth_04.mp3":{"previous_count":1,"current_count":2,"delta":1},"hornet_kill_synth_05.mp3":{"previous_count":1,"current_count":2,"delta":1},"hornet_kill_tengu_01.mp3":{"previous_count":0,"current_count":1,"delta":1},"hornet_kill_tengu_03.mp3":{"previous_count":0,"current_count":1,"delta":1},"hornet_kill_tengu_04.mp3":{"previous_count":0,"current_count":1,"delta":1},"hornet_kill_tengu_05.mp3":{"previous_count":0,"current_count":1,"delta":1},"hornet_kill_vampirebat_01.mp3":{"previous_count":1,"current_count":2,"delta":1},"hornet_kill_vampirebat_02.mp3":{"previous_count":1,"current_count":2,"delta":1},"hornet_kill_vampirebat_03.mp3":{"previous_count":1,"current_count":2,"delta":1},"hornet_kill_vampirebat_04.mp3":{"previous_count":3,"current_count":4,"delta":1},"hornet_kill_vampirebat_05.mp3":{"previous_count":1,"current_count":2,"delta":1},"hornet_kill_viper_01.mp3":{"previous_count":0,"current_count":1,"delta":1},"hornet_kill_viper_02.mp3":{"previous_count":1,"current_count":2,"delta":1},"hornet_kill_viper_03.mp3":{"previous_count":0,"current_count":1,"delta":1},"hornet_kill_viper_04.mp3":{"previous_count":0,"current_count":1,"delta":1},"hornet_kill_viscous_01.mp3":{"previous_count":1,"current_count":2,"delta":1},"hornet_kill_viscous_03.mp3":{"previous_count":0,"current_count":1,"delta":1},"hornet_kill_viscous_04.mp3":{"previous_count":0,"current_count":1,"delta":1},"hornet_kill_viscous_05.mp3":{"previous_count":0,"current_count":1,"delta":1},"hornet_kill_warden_01.mp3":{"previous_count":2,"current_count":3,"delta":1},"hornet_kill_warden_04.mp3":{"previous_count":2,"current_count":3,"delta":1},"hornet_kill_wraith_01.mp3":{"previous_count":0,"current_count":1,"delta":1},"hornet_kill_wraith_02.mp3":{"previous_count":0,"current_count":1,"delta":1},"hornet_kill_wraith_03.mp3":{"previous_count":0,"current_count":1,"delta":1},"hornet_kill_yamato_01.mp3":{"previous_count":2,"current_count":3,"delta":1},"hornet_kill_yamato_03.mp3":{"previous_count":1,"current_count":2,"delta":1},"hornet_kill_yamato_04.mp3":{"previous_count":0,"current_count":1,"delta":1},"hornet_kill_yamato_05.mp3":{"previous_count":2,"current_count":3,"delta":1},"hornet_ping_attack_hornet.mp3":{"previous_count":4,"current_count":5,"delta":1},"hornet_ping_careful_drifter_01.mp3":{"previous_count":0,"current_count":1,"delta":1},"hornet_ping_careful_drifter_02.mp3":{"previous_count":0,"current_count":1,"delta":1},"hornet_ping_careful_drifter_03.mp3":{"previous_count":0,"current_count":1,"delta":1},"hornet_ping_careful_orion_01.mp3":{"previous_count":0,"current_count":1,"delta":1},"inferno_ally_gigawatt_multi_kill_ult_01.mp3":{"previous_count":2,"current_count":3,"delta":1},"inferno_ally_gigawatt_multi_kill_ult_02.mp3":{"previous_count":1,"current_count":2,"delta":1},"inferno_ally_gigawatt_multi_kill_ult_03.mp3":{"previous_count":1,"current_count":2,"delta":1},"inferno_ally_lash_see_massive_stomp_01.mp3":{"previous_count":1,"current_count":2,"delta":1},"inferno_ally_lash_see_massive_stomp_02.mp3":{"previous_count":0,"current_count":1,"delta":1},"inferno_ally_lash_see_massive_stomp_03.mp3":{"previous_count":1,"current_count":2,"delta":1},"inferno_enemy_lash_mid_air_kill_01.mp3":{"previous_count":2,"current_count":3,"delta":1},"inferno_enemy_lash_mid_air_kill_02.mp3":{"previous_count":2,"current_count":3,"delta":1},"inferno_enemy_lash_mid_air_kill_03.mp3":{"previous_count":1,"current_count":2,"delta":1},"kelvin_ally_gigawatt_multi_kill_ult_01.mp3":{"previous_count":1,"current_count":2,"delta":1},"kelvin_ally_gigawatt_multi_kill_ult_02.mp3":{"previous_count":1,"current_count":2,"delta":1},"kelvin_ally_gigawatt_multi_kill_ult_03.mp3":{"previous_count":1,"current_count":2,"delta":1},"kelvin_desperation_power1_01.mp3":{"previous_count":3,"current_count":4,"delta":1},"kelvin_desperation_power1_02.mp3":{"previous_count":0,"current_count":1,"delta":1},"kelvin_desperation_power1_03.mp3":{"previous_count":0,"current_count":1,"delta":1},"kelvin_desperation_power1_04.mp3":{"previous_count":0,"current_count":1,"delta":1},"kelvin_desperation_power2_01.mp3":{"previous_count":0,"current_count":1,"delta":1},"kelvin_desperation_power2_02.mp3":{"previous_count":0,"current_count":1,"delta":1},"kelvin_desperation_power3_01.mp3":{"previous_count":1,"current_count":2,"delta":1},"kelvin_desperation_power3_02.mp3":{"previous_count":0,"current_count":1,"delta":1},"kelvin_desperation_power3_03.mp3":{"previous_count":0,"current_count":1,"delta":1},"kelvin_desperation_power3_04.mp3":{"previous_count":0,"current_count":1,"delta":1},"kelvin_desperation_power4_01.mp3":{"previous_count":3,"current_count":4,"delta":1},"kelvin_desperation_power4_02.mp3":{"previous_count":1,"current_count":2,"delta":1},"kelvin_desperation_power4_03.mp3":{"previous_count":1,"current_count":2,"delta":1},"kelvin_desperation_power4_04.mp3":{"previous_count":1,"current_count":2,"delta":1},"kelvin_desperation_power4_05.mp3":{"previous_count":0,"current_count":1,"delta":1},"kelvin_killstreak_high_01.mp3":{"previous_count":3,"current_count":4,"delta":1},"kelvin_killstreak_high_02.mp3":{"previous_count":3,"current_count":4,"delta":1},"kelvin_killstreak_high_03.mp3":{"previous_count":3,"current_count":4,"delta":1},"kelvin_use_power4_01.mp3":{"previous_count":0,"current_count":1,"delta":1},"kelvin_use_power4_02.mp3":{"previous_count":0,"current_count":1,"delta":1},"kelvin_use_power4_03.mp3":{"previous_count":0,"current_count":1,"delta":1},"kelvin_use_power4_04.mp3":{"previous_count":0,"current_count":1,"delta":1},"kelvin_use_power4_05.mp3":{"previous_count":0,"current_count":1,"delta":1},"kelvin_use_power4_06.mp3":{"previous_count":0,"current_count":1,"delta":1},"kelvin_use_power4_07.mp3":{"previous_count":0,"current_count":1,"delta":1},"kelvin_use_power4_08.mp3":{"previous_count":1,"current_count":2,"delta":1},"kelvin_use_power4_09.mp3":{"previous_count":2,"current_count":3,"delta":1},"kelvin_use_power4_10.mp3":{"previous_count":0,"current_count":1,"delta":1},"krill_ally_gigawatt_multi_kill_ult_01.mp3":{"previous_count":0,"current_count":1,"delta":1},"krill_ally_gigawatt_multi_kill_ult_02.mp3":{"previous_count":1,"current_count":2,"delta":1},"krill_ally_gigawatt_multi_kill_ult_03.mp3":{"previous_count":1,"current_count":2,"delta":1},"nano_ally_gigawatt_multi_kill_ult_01.mp3":{"previous_count":0,"current_count":1,"delta":1},"nano_ally_gigawatt_multi_kill_ult_03.mp3":{"previous_count":0,"current_count":1,"delta":1},"nano_ally_lash_see_massive_stomp_01.mp3":{"previous_count":2,"current_count":3,"delta":1},"nano_ally_lash_see_massive_stomp_02.mp3":{"previous_count":1,"current_count":2,"delta":1},"nano_ally_lash_see_massive_stomp_03.mp3":{"previous_count":1,"current_count":2,"delta":1},"nano_enemy_lash_mid_air_kill_01.mp3":{"previous_count":1,"current_count":2,"delta":1},"nano_enemy_lash_mid_air_kill_02.mp3":{"previous_count":1,"current_count":2,"delta":1},"nano_enemy_lash_mid_air_kill_03.mp3":{"previous_count":1,"current_count":2,"delta":1},"orion_ally_gigawatt_multi_kill_ult_01.mp3":{"previous_count":2,"current_count":3,"delta":1},"orion_ally_gigawatt_multi_kill_ult_02.mp3":{"previous_count":0,"current_count":1,"delta":1},"orion_ally_gigawatt_multi_kill_ult_03.mp3":{"previous_count":1,"current_count":2,"delta":1},"orion_ally_lash_killed_in_lane_01.mp3":{"previous_count":2,"current_count":3,"delta":1},"orion_ally_lash_see_massive_stomp_01.mp3":{"previous_count":1,"current_count":2,"delta":1},"orion_ally_lash_see_massive_stomp_02.mp3":{"previous_count":1,"current_count":2,"delta":1},"orion_ally_lash_see_massive_stomp_03.mp3":{"previous_count":1,"current_count":2,"delta":1},"orion_desperation_power1_01.mp3":{"previous_count":0,"current_count":1,"delta":1},"orion_desperation_power1_02.mp3":{"previous_count":0,"current_count":1,"delta":1},"orion_desperation_power4_01.mp3":{"previous_count":1,"current_count":2,"delta":1},"orion_desperation_power4_02.mp3":{"previous_count":1,"current_count":2,"delta":1},"orion_desperation_power4_03.mp3":{"previous_count":2,"current_count":3,"delta":1},"orion_desperation_power4_04.mp3":{"previous_count":2,"current_count":3,"delta":1},"orion_desperation_power4_05.mp3":{"previous_count":2,"current_count":3,"delta":1},"orion_enemy_lash_mid_air_kill_01.mp3":{"previous_count":3,"current_count":4,"delta":1},"orion_enemy_lash_mid_air_kill_02.mp3":{"previous_count":2,"current_count":3,"delta":1},"orion_enemy_lash_mid_air_kill_03.mp3":{"previous_count":2,"current_count":3,"delta":1},"orion_killstreak_high_01.mp3":{"previous_count":4,"current_count":5,"delta":1},"orion_killstreak_high_02.mp3":{"previous_count":4,"current_count":5,"delta":1},"orion_killstreak_high_03.mp3":{"previous_count":7,"current_count":8,"delta":1},"orion_killstreak_mid_01.mp3":{"previous_count":1,"current_count":2,"delta":1},"orion_killstreak_mid_02.mp3":{"previous_count":1,"current_count":2,"delta":1},"orion_killstreak_mid_03.mp3":{"previous_count":2,"current_count":3,"delta":1},"orion_killstreak_start_01.mp3":{"previous_count":1,"current_count":2,"delta":1},"orion_killstreak_start_02.mp3":{"previous_count":1,"current_count":2,"delta":1},"orion_killstreak_start_03.mp3":{"previous_count":1,"current_count":2,"delta":1},"orion_killstreak_start_04.mp3":{"previous_count":1,"current_count":2,"delta":1},"orion_killstreak_start_05.mp3":{"previous_count":1,"current_count":2,"delta":1},"patron_female_ally_doorman_start_01.mp3":{"previous_count":15,"current_count":16,"delta":1},"patron_female_ally_doorman_start_02.mp3":{"previous_count":11,"current_count":12,"delta":1},"patron_female_ally_frank_start_01.mp3":{"previous_count":0,"current_count":2,"delta":2},"patron_female_ally_kelvin_start_01.mp3":{"previous_count":0,"current_count":1,"delta":1},"patron_female_ally_krill_killing_streak_01.mp3":{"previous_count":0,"current_count":1,"delta":1},"patron_female_ally_krill_killing_streak_02.mp3":{"previous_count":0,"current_count":1,"delta":1},"patron_female_ally_krill_killing_streak_03.mp3":{"previous_count":0,"current_count":1,"delta":1},"patron_female_ally_punkgoat_start_01.mp3":{"previous_count":2,"current_count":3,"delta":1},"patron_female_ally_punkgoat_start_05.mp3":{"previous_count":0,"current_count":1,"delta":1},"patron_female_ally_shiv_killing_streak_01.mp3":{"previous_count":3,"current_count":4,"delta":1},"patron_female_ally_shiv_killing_streak_02.mp3":{"previous_count":8,"current_count":10,"delta":2},"patron_female_ally_shiv_start_01.mp3":{"previous_count":2,"current_count":3,"delta":1},"patron_female_ally_shiv_start_02.mp3":{"previous_count":1,"current_count":2,"delta":1},"patron_female_ally_shiv_start_03.mp3":{"previous_count":3,"current_count":4,"delta":1},"patron_female_ally_shiv_start_04_alt_01.mp3":{"previous_count":0,"current_count":1,"delta":1},"patron_female_ally_shiv_start_04.mp3":{"previous_count":2,"current_count":3,"delta":1},"patron_female_ally_shiv_start_05.mp3":{"previous_count":0,"current_count":1,"delta":1},"patron_female_ally_shiv_start_06.mp3":{"previous_count":1,"current_count":2,"delta":1},"patron_female_ally_shiv_start_07.mp3":{"previous_count":2,"current_count":3,"delta":1},"patron_female_ally_viper_killing_streak_02.mp3":{"previous_count":4,"current_count":5,"delta":1},"patron_female_bespoke_ally_update_frank.mp3":{"previous_count":0,"current_count":1,"delta":1},"patron_female_bespoke_ally_update_krill.mp3":{"previous_count":0,"current_count":1,"delta":1},"patron_female_bespoke_ally_update_shiv.mp3":{"previous_count":3,"current_count":4,"delta":1},"patron_female_bespoke_enemy_update_gigawatt.mp3":{"previous_count":1,"current_count":3,"delta":2},"patron_female_bespoke_enemy_update_krill.mp3":{"previous_count":0,"current_count":1,"delta":1},"patron_female_bespoke_for_shiv.mp3":{"previous_count":2,"current_count":3,"delta":1},"patron_female_enemy_krill_killing_streak_high_01.mp3":{"previous_count":0,"current_count":1,"delta":1},"patron_female_enemy_krill_killing_streak_low_01.mp3":{"previous_count":0,"current_count":1,"delta":1},"patron_female_enemy_krill_killing_streak_medium_01.mp3":{"previous_count":0,"current_count":1,"delta":1},"patron_male_ally_bookworm_start_01_alt.mp3":{"previous_count":3,"current_count":4,"delta":1},"patron_male_ally_bookworm_start_02_alt.mp3":{"previous_count":1,"current_count":2,"delta":1},"patron_male_ally_bookworm_start_03_alt.mp3":{"previous_count":1,"current_count":2,"delta":1},"patron_male_ally_bookworm_start_04_alt.mp3":{"previous_count":3,"current_count":4,"delta":1},"patron_male_ally_bookworm_start_05_alt.mp3":{"previous_count":1,"current_count":2,"delta":1},"patron_male_ally_frank_start_01.mp3":{"previous_count":1,"current_count":3,"delta":2},"patron_male_ally_frank_start_02.mp3":{"previous_count":1,"current_count":2,"delta":1},"patron_male_ally_frank_start_03.mp3":{"previous_count":0,"current_count":1,"delta":1},"patron_male_ally_frank_start_04.mp3":{"previous_count":1,"current_count":2,"delta":1},"patron_male_ally_frank_start_05.mp3":{"previous_count":0,"current_count":1,"delta":1},"patron_male_ally_krill_killing_streak_03.mp3":{"previous_count":1,"current_count":2,"delta":1},"patron_male_ally_punkgoat_killing_streak_01.mp3":{"previous_count":4,"current_count":5,"delta":1},"patron_male_ally_punkgoat_killing_streak_02.mp3":{"previous_count":1,"current_count":2,"delta":1},"patron_male_ally_punkgoat_killing_streak_03.mp3":{"previous_count":3,"current_count":4,"delta":1},"patron_male_ally_punkgoat_start_01.mp3":{"previous_count":4,"current_count":5,"delta":1},"patron_male_ally_punkgoat_start_02.mp3":{"previous_count":2,"current_count":3,"delta":1},"patron_male_ally_punkgoat_start_03.mp3":{"previous_count":1,"current_count":2,"delta":1},"patron_male_ally_shiv_start_01.mp3":{"previous_count":2,"current_count":3,"delta":1},"patron_male_ally_shiv_start_02.mp3":{"previous_count":3,"current_count":4,"delta":1},"patron_male_ally_shiv_start_03.mp3":{"previous_count":3,"current_count":4,"delta":1},"patron_male_ally_shiv_start_04.mp3":{"previous_count":0,"current_count":1,"delta":1},"patron_male_ally_shiv_start_05.mp3":{"previous_count":2,"current_count":3,"delta":1},"patron_male_ally_warden_start_03.mp3":{"previous_count":7,"current_count":8,"delta":1},"patron_male_enemy_krill_killing_streak_high_01.mp3":{"previous_count":2,"current_count":3,"delta":1},"patron_male_enemy_krill_killing_streak_low_01.mp3":{"previous_count":2,"current_count":3,"delta":1},"patron_male_enemy_krill_killing_streak_medium_01.mp3":{"previous_count":3,"current_count":4,"delta":1},"patron_male_enemy_punkgoat_killing_streak_high_01.mp3":{"previous_count":13,"current_count":14,"delta":1},"punkgoat_ally_gigawatt_multi_kill_ult_01.mp3":{"previous_count":2,"current_count":3,"delta":1},"punkgoat_ally_gigawatt_multi_kill_ult_02.mp3":{"previous_count":0,"current_count":1,"delta":1},"punkgoat_ally_gigawatt_multi_kill_ult_03.mp3":{"previous_count":2,"current_count":3,"delta":1},"punkgoat_ally_lash_see_massive_stomp_01.mp3":{"previous_count":3,"current_count":4,"delta":1},"punkgoat_ally_lash_see_massive_stomp_02.mp3":{"previous_count":3,"current_count":4,"delta":1},"punkgoat_ally_lash_see_massive_stomp_03.mp3":{"previous_count":2,"current_count":3,"delta":1},"punkgoat_enemy_gigawatt_hide_from_ult_01.mp3":{"previous_count":1,"current_count":2,"delta":1},"punkgoat_enemy_gigawatt_hide_from_ult_03.mp3":{"previous_count":1,"current_count":2,"delta":1},"punkgoat_enemy_lash_mid_air_kill_01.mp3":{"previous_count":2,"current_count":3,"delta":1},"punkgoat_enemy_lash_mid_air_kill_02.mp3":{"previous_count":2,"current_count":3,"delta":1},"punkgoat_enemy_lash_mid_air_kill_03.mp3":{"previous_count":2,"current_count":3,"delta":1},"shiv_desperation_power2_01.mp3":{"previous_count":6,"current_count":7,"delta":1},"shiv_desperation_power2_05.mp3":{"previous_count":6,"current_count":8,"delta":2},"shiv_desperation_power4_01.mp3":{"previous_count":7,"current_count":8,"delta":1},"shiv_desperation_power4_02.mp3":{"previous_count":8,"current_count":9,"delta":1},"shiv_desperation_power4_03.mp3":{"previous_count":7,"current_count":8,"delta":1},"shiv_desperation_power4_04.mp3":{"previous_count":7,"current_count":8,"delta":1},"shiv_desperation_power4_05.mp3":{"previous_count":7,"current_count":9,"delta":2},"shiv_killstreak_high_01.mp3":{"previous_count":9,"current_count":10,"delta":1},"shiv_killstreak_high_02.mp3":{"previous_count":8,"current_count":9,"delta":1},"shiv_killstreak_high_03.mp3":{"previous_count":8,"current_count":9,"delta":1},"shiv_killstreak_mid_01.mp3":{"previous_count":5,"current_count":6,"delta":1},"shiv_killstreak_mid_03.mp3":{"previous_count":9,"current_count":10,"delta":1},"shiv_leave_base_01.mp3":{"previous_count":5,"current_count":6,"delta":1},"shiv_leave_base_02.mp3":{"previous_count":4,"current_count":5,"delta":1},"shiv_ping_pre_game_01.mp3":{"previous_count":4,"current_count":5,"delta":1},"shiv_ping_pre_game_02.mp3":{"previous_count":4,"current_count":5,"delta":1},"shiv_ping_pre_game_05.mp3":{"previous_count":3,"current_count":4,"delta":1},"shiv_select_01.mp3":{"previous_count":5,"current_count":6,"delta":1},"shiv_select_03.mp3":{"previous_count":4,"current_count":5,"delta":1},"shiv_use_power2_01.mp3":{"previous_count":3,"current_count":4,"delta":1},"shiv_use_power2_04.mp3":{"previous_count":3,"current_count":4,"delta":1},"shiv_use_power2_05.mp3":{"previous_count":3,"current_count":4,"delta":1},"shiv_use_power2_06.mp3":{"previous_count":3,"current_count":4,"delta":1},"shiv_use_power4_03.mp3":{"previous_count":8,"current_count":9,"delta":1},"shiv_use_power4_04.mp3":{"previous_count":9,"current_count":10,"delta":1},"shiv_use_power4_05.mp3":{"previous_count":6,"current_count":7,"delta":1},"shiv_use_power4_06.mp3":{"previous_count":5,"current_count":6,"delta":1},"shiv_use_power4_07.mp3":{"previous_count":6,"current_count":7,"delta":1},"shiv_use_power4_10.mp3":{"previous_count":8,"current_count":9,"delta":1},"shopkeeper_hotdog_t4_gigawatt_01.mp3":{"previous_count":2,"current_count":3,"delta":1},"shopkeeper_hotdog_t4_gigawatt_02.mp3":{"previous_count":3,"current_count":4,"delta":1},"slork_ping_attack_lash.mp3":{"previous_count":0,"current_count":6,"delta":6},"tengu_ally_gigawatt_multi_kill_ult_01.mp3":{"previous_count":0,"current_count":1,"delta":1},"tengu_ally_gigawatt_multi_kill_ult_02.mp3":{"previous_count":0,"current_count":1,"delta":1},"tengu_ally_gigawatt_multi_kill_ult_03.mp3":{"previous_count":0,"current_count":1,"delta":1},"tengu_ally_lash_killed_in_lane_01.mp3":{"previous_count":0,"current_count":1,"delta":1},"tengu_ally_lash_see_massive_stomp_01.mp3":{"previous_count":0,"current_count":1,"delta":1},"tengu_match_start_drifter_tengu_convo03_02.mp3":{"previous_count":24,"current_count":25,"delta":1},"tengu_match_start_drifter_tengu_convo03_04.mp3":{"previous_count":16,"current_count":17,"delta":1},"vampirebat_ally_gigawatt_multi_kill_ult_01.mp3":{"previous_count":1,"current_count":2,"delta":1},"vampirebat_ally_gigawatt_multi_kill_ult_02.mp3":{"previous_count":1,"current_count":2,"delta":1},"vampirebat_ally_gigawatt_multi_kill_ult_03.mp3":{"previous_count":3,"current_count":4,"delta":1},"viscous_ally_gigawatt_multi_kill_ult_01.mp3":{"previous_count":1,"current_count":2,"delta":1},"viscous_ally_gigawatt_multi_kill_ult_02.mp3":{"previous_count":1,"current_count":2,"delta":1},"viscous_ally_gigawatt_multi_kill_ult_03.mp3":{"previous_count":1,"current_count":2,"delta":1},"warden_ally_gigawatt_multi_kill_ult_01.mp3":{"previous_count":2,"current_count":3,"delta":1},"warden_ally_gigawatt_multi_kill_ult_02.mp3":{"previous_count":2,"current_count":3,"delta":1},"warden_ally_gigawatt_multi_kill_ult_03.mp3":{"previous_count":3,"current_count":4,"delta":1},"warden_enemy_gigawatt_hide_from_ult_01.mp3":{"previous_count":1,"current_count":2,"delta":1},"warden_enemy_gigawatt_hide_from_ult_02.mp3":{"previous_count":2,"current_count":3,"delta":1},"warden_enemy_gigawatt_hide_from_ult_03.mp3":{"previous_count":1,"current_count":2,"delta":1},"wraith_ally_gigawatt_multi_kill_ult_01.mp3":{"previous_count":0,"current_count":1,"delta":1},"wraith_ally_gigawatt_multi_kill_ult_02.mp3":{"previous_count":0,"current_count":1,"delta":1},"wraith_ally_gigawatt_multi_kill_ult_03.mp3":{"previous_count":0,"current_count":1,"delta":1},"yamato_kill_gigawatt_01.mp3":{"previous_count":1,"current_count":2,"delta":1},"yamato_kill_gigawatt_03.mp3":{"previous_count":0,"current_count":1,"delta":1},"yamato_kill_gigawatt_04.mp3":{"previous_count":1,"current_count":2,"delta":1},"yamato_kill_gigawatt_05.mp3":{"previous_count":0,"current_count":1,"delta":1}},"conversations":{"drifter_ivy_convo03":{"previous_count":60,"current_count":62,"delta":2}},"character_totals":{"abrams":{"previous_count":599,"current_count":615,"delta":16},"bebop":{"previous_count":537,"current_count":541,"delta":4},"billy":{"previous_count":418,"current_count":433,"delta":15},"calico":{"previous_count":267,"current_count":275,"delta":8},"doorman":{"previous_count":579,"current_count":593,"delta":14},"drifter":{"previous_count":376,"current_count":386,"delta":10},"dynamo":{"previous_count":263,"current_count":275,"delta":12},"fathom":{"previous_count":98,"current_count":104,"delta":6},"grey talon":{"previous_count":333,"current_count":350,"delta":17},"haze":{"previous_count":340,"current_count":349,"delta":9},"holliday":{"previous_count":351,"current_count":360,"delta":9},"infernus":{"previous_count":248,"current_count":261,"delta":13},"ivy":{"previous_count":284,"current_count":293,"delta":9},"kelvin":{"previous_count":228,"current_count":232,"delta":4},"krill":{"previous_count":297,"current_count":315,"delta":18},"lady geist":{"previous_count":295,"current_count":297,"delta":2},"lash":{"previous_count":508,"current_count":513,"delta":5},"mina":{"previous_count":397,"current_count":405,"delta":8},"mirage":{"previous_count":238,"current_count":241,"delta":3},"paige":{"previous_count":283,"current_count":293,"delta":10},"patron female":{"previous_count":253,"current_count":255,"delta":2},"pocket":{"previous_count":400,"current_count":405,"delta":5},"priest":{"previous_count":262,"current_count":267,"delta":5},"seven":{"previous_count":313,"current_count":321,"delta":8},"shiv":{"previous_count":367,"current_count":389,"delta":22},"shopkeeper_hotdog":{"previous_count":37,"current_count":39,"delta":2},"victor":{"previous_count":312,"current_count":329,"delta":17},"vindicta":{"previous_count":204,"current_count":205,"delta":1},"viper":{"previous_count":297,"current_count":302,"delta":5},"viscous":{"previous_count":302,"current_count":309,"delta":7},"warden":{"previous_count":176,"current_count":185,"delta":9},"wraith":{"previous_count":184,"current_count":190,"delta":6},"yamato":{"previous_count":259,"current_count":267,"delta":8}}}}}